{"001\/23":{"dl_date":1678317284,"dl_url":"https:\/\/www.mynavyhr.navy.mil\/Portals\/55\/Messages\/NAVADMIN\/NAV2023\/NAV23001.txt"},"001\/24":{"dl_date":1709249342,"dl_url":"https:\/\/www.mynavyhr.navy.mil\/Portals\/55\/Messages\/NAVADMIN\/NAV2024\/NAV24001.txt"},"002\/23":{"dl_date":1674095166,"dl_url":"https:\/\/www.mynavyhr.navy.mil\/Portals\/55\/Messages\/NAVADMIN\/NAV2023\/NAV23002.txt"},"002\/24":{"dl_date":1704492623,"dl_url":"https:\/\/www.mynavyhr.navy.mil\/Portals\/55\/Messages\/NAVADMIN\/NAV2024\/NAV24002.txt"},"002\/25":{"dl_date":1736966815,"dl_url":"https:\/\/www.mynavyhr.navy.mil\/Portals\/55\/Messages\/NAVADMIN\/NAV2025\/NAV25002.txt"},"003\/23":{"dl_date":1673482682,"dl_url":"https:\/\/www.mynavyhr.navy.mil\/Portals\/55\/Messages\/NAVADMIN\/NAV2023\/NAV23003.txt"},"003\/24":{"dl_date":1704840651,"dl_url":"https:\/\/www.mynavyhr.navy.mil\/Portals\/55\/Messages\/NAVADMIN\/NAV2024\/NAV24003.txt"},"003\/25":{"dl_date":1736966815,"dl_url":"https:\/\/www.mynavyhr.navy.mil\/Portals\/55\/Messages\/NAVADMIN\/NAV2025\/NAV25003.txt"},"004\/23":{"dl_date":1673482682,"dl_url":"https:\/\/www.mynavyhr.navy.mil\/Portals\/55\/Messages\/NAVADMIN\/NAV2023\/NAV23004.txt"},"004\/24":{"dl_date":1705008011,"dl_url":"https:\/\/www.mynavyhr.navy.mil\/Portals\/55\/Messages\/NAVADMIN\/NAV2024\/NAV24004.txt"},"004\/25":{"dl_date":1736966815,"dl_url":"https:\/\/www.mynavyhr.navy.mil\/Portals\/55\/Messages\/NAVADMIN\/NAV2025\/NAV25004.txt"},"005\/23":{"dl_date":1673615486,"dl_url":"https:\/\/www.mynavyhr.navy.mil\/Portals\/55\/Messages\/NAVADMIN\/NAV2023\/NAV23005.txt"},"005\/24":{"dl_date":1705155837,"dl_url":"https:\/\/www.mynavyhr.navy.mil\/Portals\/55\/Messages\/NAVADMIN\/NAV2024\/NAV24005.txt"},"005\/25":{"dl_date":1737165496,"dl_url":"https:\/\/www.mynavyhr.navy.mil\/Portals\/55\/Messages\/NAVADMIN\/NAV2025\/NAV25005.txt"},"006\/23":{"dl_date":1674001612,"dl_url":"https:\/\/www.mynavyhr.navy.mil\/Portals\/55\/Messages\/NAVADMIN\/NAV2023\/NAV23006.txt"},"006\/24":{"dl_date":1705443410,"dl_url":"https:\/\/www.mynavyhr.navy.mil\/Portals\/55\/Messages\/NAVADMIN\/NAV2024\/NAV24006.txt"},"006\/25":{"dl_date":1737578259,"dl_url":"https:\/\/www.mynavyhr.navy.mil\/Portals\/55\/Messages\/NAVADMIN\/NAV2025\/NAV25006.txt"},"007\/23":{"dl_date":1675305733,"dl_url":"https:\/\/www.mynavyhr.navy.mil\/Portals\/55\/Messages\/NAVADMIN\/NAV2023\/NAV23007.txt"},"007\/24":{"dl_date":1705616722,"dl_url":"https:\/\/www.mynavyhr.navy.mil\/Portals\/55\/Messages\/NAVADMIN\/NAV2024\/NAV24007.txt"},"007\/25":{"dl_date":1737578259,"dl_url":"https:\/\/www.mynavyhr.navy.mil\/Portals\/55\/Messages\/NAVADMIN\/NAV2025\/NAV25007.txt"},"008\/23":{"dl_date":1674175622,"dl_url":"https:\/\/www.mynavyhr.navy.mil\/Portals\/55\/Messages\/NAVADMIN\/NAV2023\/NAV23008.txt"},"008\/24":{"dl_date":1705698160,"dl_url":"https:\/\/www.mynavyhr.navy.mil\/Portals\/55\/Messages\/NAVADMIN\/NAV2024\/NAV24008.txt"},"008\/25":{"dl_date":1737578259,"dl_url":"https:\/\/www.mynavyhr.navy.mil\/Portals\/55\/Messages\/NAVADMIN\/NAV2025\/NAV25008.txt"},"009\/23":{"dl_date":1674261843,"dl_url":"https:\/\/www.mynavyhr.navy.mil\/Portals\/55\/Messages\/NAVADMIN\/NAV2023\/NAV23009.txt"},"009\/24":{"dl_date":1705698160,"dl_url":"https:\/\/www.mynavyhr.navy.mil\/Portals\/55\/Messages\/NAVADMIN\/NAV2024\/NAV24009.txt"},"009\/25":{"dl_date":1737578259,"dl_url":"https:\/\/www.mynavyhr.navy.mil\/Portals\/55\/Messages\/NAVADMIN\/NAV2025\/NAV25009.txt"},"010\/23":{"dl_date":1674533176,"dl_url":"https:\/\/www.mynavyhr.navy.mil\/Portals\/55\/Messages\/NAVADMIN\/NAV2023\/NAV23010.txt"},"010\/24":{"dl_date":1705698161,"dl_url":"https:\/\/www.mynavyhr.navy.mil\/Portals\/55\/Messages\/NAVADMIN\/NAV2024\/NAV24010.txt"},"010\/25":{"dl_date":1738603964,"dl_url":"https:\/\/www.mynavyhr.navy.mil\/Portals\/55\/Messages\/NAVADMIN\/NAV2025\/NAV25010.txt"},"011\/23":{"dl_date":1674533175,"dl_url":"https:\/\/www.mynavyhr.navy.mil\/Portals\/55\/Messages\/NAVADMIN\/NAV2023\/NAV23011.txt"},"011\/24":{"dl_date":1705698160,"dl_url":"https:\/\/www.mynavyhr.navy.mil\/Portals\/55\/Messages\/NAVADMIN\/NAV2024\/NAV24011.txt"},"011\/25":{"dl_date":1737578259,"dl_url":"https:\/\/www.mynavyhr.navy.mil\/Portals\/55\/Messages\/NAVADMIN\/NAV2025\/NAV25011.txt"},"012\/23":{"dl_date":1674533175,"dl_url":"https:\/\/www.mynavyhr.navy.mil\/Portals\/55\/Messages\/NAVADMIN\/NAV2023\/NAV23012.txt"},"012\/24":{"dl_date":1705964668,"dl_url":"https:\/\/www.mynavyhr.navy.mil\/Portals\/55\/Messages\/NAVADMIN\/NAV2024\/NAV24012.txt"},"012\/25":{"dl_date":1737578259,"dl_url":"https:\/\/www.mynavyhr.navy.mil\/Portals\/55\/Messages\/NAVADMIN\/NAV2025\/NAV25012.txt"},"013\/23":{"dl_date":1674533175,"dl_url":"https:\/\/www.mynavyhr.navy.mil\/Portals\/55\/Messages\/NAVADMIN\/NAV2023\/NAV23013.txt"},"013\/24":{"dl_date":1705964668,"dl_url":"https:\/\/www.mynavyhr.navy.mil\/Portals\/55\/Messages\/NAVADMIN\/NAV2024\/NAV24013.txt"},"013\/25":{"dl_date":1737731291,"dl_url":"https:\/\/www.mynavyhr.navy.mil\/Portals\/55\/Messages\/NAVADMIN\/NAV2025\/NAV25013.txt"},"014\/23":{"dl_date":1674610762,"dl_url":"https:\/\/www.mynavyhr.navy.mil\/Portals\/55\/Messages\/NAVADMIN\/NAV2023\/NAV23014.txt"},"014\/24":{"dl_date":1706144429,"dl_url":"https:\/\/www.mynavyhr.navy.mil\/Portals\/55\/Messages\/NAVADMIN\/NAV2024\/NAV24014.txt"},"014\/25":{"dl_date":1737820541,"dl_url":"https:\/\/www.mynavyhr.navy.mil\/Portals\/55\/Messages\/NAVADMIN\/NAV2025\/NAV25014.txt"},"015\/23":{"dl_date":1675130439,"dl_url":"https:\/\/www.mynavyhr.navy.mil\/Portals\/55\/Messages\/NAVADMIN\/NAV2023\/NAV23015.txt"},"015\/24":{"dl_date":1706144429,"dl_url":"https:\/\/www.mynavyhr.navy.mil\/Portals\/55\/Messages\/NAVADMIN\/NAV2024\/NAV24015.txt"},"015\/25":{"dl_date":1737820541,"dl_url":"https:\/\/www.mynavyhr.navy.mil\/Portals\/55\/Messages\/NAVADMIN\/NAV2025\/NAV25015.txt"},"016\/23":{"dl_date":1675130439,"dl_url":"https:\/\/www.mynavyhr.navy.mil\/Portals\/55\/Messages\/NAVADMIN\/NAV2023\/NAV23016.txt"},"016\/24":{"dl_date":1706570718,"dl_url":"https:\/\/www.mynavyhr.navy.mil\/Portals\/55\/Messages\/NAVADMIN\/NAV2024\/NAV24016.txt"},"016\/25":{"dl_date":1737847747,"dl_url":"https:\/\/www.mynavyhr.navy.mil\/Portals\/55\/Messages\/NAVADMIN\/NAV2025\/NAV25016.txt"},"017\/23":{"dl_date":1675130439,"dl_url":"https:\/\/www.mynavyhr.navy.mil\/Portals\/55\/Messages\/NAVADMIN\/NAV2023\/NAV23017.txt"},"017\/24":{"dl_date":1706829957,"dl_url":"https:\/\/www.mynavyhr.navy.mil\/Portals\/55\/Messages\/NAVADMIN\/NAV2024\/NAV24017.txt"},"017\/25":{"dl_date":1738440610,"dl_url":"https:\/\/www.mynavyhr.navy.mil\/Portals\/55\/Messages\/NAVADMIN\/NAV2025\/NAV25017.txt"},"018\/23":{"dl_date":1675305732,"dl_url":"https:\/\/www.mynavyhr.navy.mil\/Portals\/55\/Messages\/NAVADMIN\/NAV2023\/NAV23018.txt"},"018\/24":{"dl_date":1707278096,"dl_url":"https:\/\/www.mynavyhr.navy.mil\/Portals\/55\/Messages\/NAVADMIN\/NAV2024\/NAV24018.txt"},"018\/25":{"dl_date":1738020538,"dl_url":"https:\/\/www.mynavyhr.navy.mil\/Portals\/55\/Messages\/NAVADMIN\/NAV2025\/NAV25018.txt"},"019\/23":{"dl_date":1675305731,"dl_url":"https:\/\/www.mynavyhr.navy.mil\/Portals\/55\/Messages\/NAVADMIN\/NAV2023\/NAV23019.txt"},"019\/24":{"dl_date":1707278096,"dl_url":"https:\/\/www.mynavyhr.navy.mil\/Portals\/55\/Messages\/NAVADMIN\/NAV2024\/NAV24019.txt"},"019\/25":{"dl_date":1738091319,"dl_url":"https:\/\/www.mynavyhr.navy.mil\/Portals\/55\/Messages\/NAVADMIN\/NAV2025\/NAV25019.txt"},"020\/23":{"dl_date":1675305731,"dl_url":"https:\/\/www.mynavyhr.navy.mil\/Portals\/55\/Messages\/NAVADMIN\/NAV2023\/NAV23020.txt"},"020\/24":{"dl_date":1707278096,"dl_url":"https:\/\/www.mynavyhr.navy.mil\/Portals\/55\/Messages\/NAVADMIN\/NAV2024\/NAV24020.txt"},"020\/25":{"dl_date":1738195533,"dl_url":"https:\/\/www.mynavyhr.navy.mil\/Portals\/55\/Messages\/NAVADMIN\/NAV2025\/NAV25020.txt"},"021\/23":{"dl_date":1675305731,"dl_url":"https:\/\/www.mynavyhr.navy.mil\/Portals\/55\/Messages\/NAVADMIN\/NAV2023\/NAV23021.txt"},"021\/24":{"dl_date":1707278095,"dl_url":"https:\/\/www.mynavyhr.navy.mil\/Portals\/55\/Messages\/NAVADMIN\/NAV2024\/NAV24021.txt"},"021\/25":{"dl_date":1738809329,"dl_url":"https:\/\/www.mynavyhr.navy.mil\/Portals\/55\/Messages\/NAVADMIN\/NAV2025\/NAV25021.txt"},"022\/23":{"dl_date":1675305731,"dl_url":"https:\/\/www.mynavyhr.navy.mil\/Portals\/55\/Messages\/NAVADMIN\/NAV2023\/NAV23022.txt"},"022\/24":{"dl_date":1707442533,"dl_url":"https:\/\/www.mynavyhr.navy.mil\/Portals\/55\/Messages\/NAVADMIN\/NAV2024\/NAV24022.txt"},"022\/25":{"dl_date":1738972275,"dl_url":"https:\/\/www.mynavyhr.navy.mil\/Portals\/55\/Messages\/NAVADMIN\/NAV2025\/NAV25022.txt"},"023\/23":{"dl_date":1675305731,"dl_url":"https:\/\/www.mynavyhr.navy.mil\/Portals\/55\/Messages\/NAVADMIN\/NAV2023\/NAV23023.txt"},"023\/24":{"dl_date":1707442533,"dl_url":"https:\/\/www.mynavyhr.navy.mil\/Portals\/55\/Messages\/NAVADMIN\/NAV2024\/NAV24023.txt"},"023\/25":{"dl_date":1738972275,"dl_url":"https:\/\/www.mynavyhr.navy.mil\/Portals\/55\/Messages\/NAVADMIN\/NAV2025\/NAV25023.txt"},"024\/23":{"dl_date":1675381859,"dl_url":"https:\/\/www.mynavyhr.navy.mil\/Portals\/55\/Messages\/NAVADMIN\/NAV2023\/NAV23024.txt"},"024\/24":{"dl_date":1707442534,"dl_url":"https:\/\/www.mynavyhr.navy.mil\/Portals\/55\/Messages\/NAVADMIN\/NAV2024\/NAV24024.txt"},"024\/25":{"dl_date":1739218366,"dl_url":"https:\/\/www.mynavyhr.navy.mil\/Portals\/55\/Messages\/NAVADMIN\/NAV2025\/NAV25024.txt"},"025\/23":{"dl_date":1675464917,"dl_url":"https:\/\/www.mynavyhr.navy.mil\/Portals\/55\/Messages\/NAVADMIN\/NAV2023\/NAV23025.txt"},"025\/24":{"dl_date":1709249341,"dl_url":"https:\/\/www.mynavyhr.navy.mil\/Portals\/55\/Messages\/NAVADMIN\/NAV2024\/NAV24025.txt"},"025\/25":{"dl_date":1739572511,"dl_url":"https:\/\/www.mynavyhr.navy.mil\/Portals\/55\/Messages\/NAVADMIN\/NAV2025\/NAV25025.txt"},"026\/23":{"dl_date":1675817736,"dl_url":"https:\/\/www.mynavyhr.navy.mil\/Portals\/55\/Messages\/NAVADMIN\/NAV2023\/NAV23026.txt"},"026\/24":{"dl_date":1709249340,"dl_url":"https:\/\/www.mynavyhr.navy.mil\/Portals\/55\/Messages\/NAVADMIN\/NAV2024\/NAV24026.txt"},"026\/25":{"dl_date":1739572511,"dl_url":"https:\/\/www.mynavyhr.navy.mil\/Portals\/55\/Messages\/NAVADMIN\/NAV2025\/NAV25026.txt"},"027\/23":{"dl_date":1675817736,"dl_url":"https:\/\/www.mynavyhr.navy.mil\/Portals\/55\/Messages\/NAVADMIN\/NAV2023\/NAV23027.txt"},"027\/24":{"dl_date":1708043842,"dl_url":"https:\/\/www.mynavyhr.navy.mil\/Portals\/55\/Messages\/NAVADMIN\/NAV2024\/NAV24027.txt"},"027\/25":{"dl_date":1739572511,"dl_url":"https:\/\/www.mynavyhr.navy.mil\/Portals\/55\/Messages\/NAVADMIN\/NAV2025\/NAV25027.txt"},"028\/23":{"dl_date":1675817736,"dl_url":"https:\/\/www.mynavyhr.navy.mil\/Portals\/55\/Messages\/NAVADMIN\/NAV2023\/NAV23028.txt"},"028\/24":{"dl_date":1707867991,"dl_url":"https:\/\/www.mynavyhr.navy.mil\/Portals\/55\/Messages\/NAVADMIN\/NAV2024\/NAV24028.txt"},"028\/25":{"dl_date":1739572511,"dl_url":"https:\/\/www.mynavyhr.navy.mil\/Portals\/55\/Messages\/NAVADMIN\/NAV2025\/NAV25028.txt"},"029\/23":{"dl_date":1675987455,"dl_url":"https:\/\/www.mynavyhr.navy.mil\/Portals\/55\/Messages\/NAVADMIN\/NAV2023\/NAV23029.txt"},"029\/24":{"dl_date":1708129045,"dl_url":"https:\/\/www.mynavyhr.navy.mil\/Portals\/55\/Messages\/NAVADMIN\/NAV2024\/NAV24029.txt"},"030\/23":{"dl_date":1675987455,"dl_url":"https:\/\/www.mynavyhr.navy.mil\/Portals\/55\/Messages\/NAVADMIN\/NAV2023\/NAV23030.txt"},"030\/24":{"dl_date":1707956746,"dl_url":"https:\/\/www.mynavyhr.navy.mil\/Portals\/55\/Messages\/NAVADMIN\/NAV2024\/NAV24030.txt"},"031\/24":{"dl_date":1707956746,"dl_url":"https:\/\/www.mynavyhr.navy.mil\/Portals\/55\/Messages\/NAVADMIN\/NAV2024\/NAV24031.txt"},"032\/23":{"dl_date":1676068069,"dl_url":"https:\/\/www.mynavyhr.navy.mil\/Portals\/55\/Messages\/NAVADMIN\/NAV2023\/NAV23032.txt"},"032\/24":{"dl_date":1707956746,"dl_url":"https:\/\/www.mynavyhr.navy.mil\/Portals\/55\/Messages\/NAVADMIN\/NAV2024\/NAV24032.txt"},"033\/23":{"dl_date":1676340135,"dl_url":"https:\/\/www.mynavyhr.navy.mil\/Portals\/55\/Messages\/NAVADMIN\/NAV2023\/NAV23033.txt"},"033\/24":{"dl_date":1708480809,"dl_url":"https:\/\/www.mynavyhr.navy.mil\/Portals\/55\/Messages\/NAVADMIN\/NAV2024\/NAV24033.txt"},"034\/23":{"dl_date":1676417054,"dl_url":"https:\/\/www.mynavyhr.navy.mil\/Portals\/55\/Messages\/NAVADMIN\/NAV2023\/NAV23034.txt"},"034\/24":{"dl_date":1708646876,"dl_url":"https:\/\/www.mynavyhr.navy.mil\/Portals\/55\/Messages\/NAVADMIN\/NAV2024\/NAV24034.txt"},"035\/23":{"dl_date":1676521107,"dl_url":"https:\/\/www.mynavyhr.navy.mil\/Portals\/55\/Messages\/NAVADMIN\/NAV2023\/NAV23035.txt"},"035\/24":{"dl_date":1708646876,"dl_url":"https:\/\/www.mynavyhr.navy.mil\/Portals\/55\/Messages\/NAVADMIN\/NAV2024\/NAV24035.txt"},"036\/23":{"dl_date":1676521107,"dl_url":"https:\/\/www.mynavyhr.navy.mil\/Portals\/55\/Messages\/NAVADMIN\/NAV2023\/NAV23036.txt"},"036\/24":{"dl_date":1708646876,"dl_url":"https:\/\/www.mynavyhr.navy.mil\/Portals\/55\/Messages\/NAVADMIN\/NAV2024\/NAV24036.txt"},"037\/23":{"dl_date":1676600351,"dl_url":"https:\/\/www.mynavyhr.navy.mil\/Portals\/55\/Messages\/NAVADMIN\/NAV2023\/NAV23037.txt"},"037\/24":{"dl_date":1709082572,"dl_url":"https:\/\/www.mynavyhr.navy.mil\/Portals\/55\/Messages\/NAVADMIN\/NAV2024\/NAV24037.txt"},"038\/23":{"dl_date":1676521107,"dl_url":"https:\/\/www.mynavyhr.navy.mil\/Portals\/55\/Messages\/NAVADMIN\/NAV2023\/NAV23038.txt"},"038\/24":{"dl_date":1709082572,"dl_url":"https:\/\/www.mynavyhr.navy.mil\/Portals\/55\/Messages\/NAVADMIN\/NAV2024\/NAV24038.txt"},"039\/23":{"dl_date":1676600351,"dl_url":"https:\/\/www.mynavyhr.navy.mil\/Portals\/55\/Messages\/NAVADMIN\/NAV2023\/NAV23039.txt"},"039\/24":{"dl_date":1709082572,"dl_url":"https:\/\/www.mynavyhr.navy.mil\/Portals\/55\/Messages\/NAVADMIN\/NAV2024\/NAV24039.txt"},"040\/23":{"dl_date":1676600351,"dl_url":"https:\/\/www.mynavyhr.navy.mil\/Portals\/55\/Messages\/NAVADMIN\/NAV2023\/NAV23040.txt"},"040\/24":{"dl_date":1709082572,"dl_url":"https:\/\/www.mynavyhr.navy.mil\/Portals\/55\/Messages\/NAVADMIN\/NAV2024\/NAV24040.txt"},"041\/23":{"dl_date":1676600351,"dl_url":"https:\/\/www.mynavyhr.navy.mil\/Portals\/55\/Messages\/NAVADMIN\/NAV2023\/NAV23041.txt"},"041\/24":{"dl_date":1709679615,"dl_url":"https:\/\/www.mynavyhr.navy.mil\/Portals\/55\/Messages\/NAVADMIN\/NAV2024\/NAV24041.txt?ver=U6KmXM0ZPOaP6D69v6QQ3g%3d%3d"},"042\/23":{"dl_date":1676600350,"dl_url":"https:\/\/www.mynavyhr.navy.mil\/Portals\/55\/Messages\/NAVADMIN\/NAV2023\/NAV23042.txt"},"042\/24":{"dl_date":1709589901,"dl_url":"https:\/\/www.mynavyhr.navy.mil\/Portals\/55\/Messages\/NAVADMIN\/NAV2024\/NAV24042.txt"},"043\/23":{"dl_date":1676600350,"dl_url":"https:\/\/www.mynavyhr.navy.mil\/Portals\/55\/Messages\/NAVADMIN\/NAV2023\/NAV23043.txt"},"043\/24":{"dl_date":1709758949,"dl_url":"https:\/\/www.mynavyhr.navy.mil\/Portals\/55\/Messages\/NAVADMIN\/NAV2024\/NAV24043.txt"},"044\/23":{"dl_date":1676600350,"dl_url":"https:\/\/www.mynavyhr.navy.mil\/Portals\/55\/Messages\/NAVADMIN\/NAV2023\/NAV23044.txt"},"044\/24":{"dl_date":1709758949,"dl_url":"https:\/\/www.mynavyhr.navy.mil\/Portals\/55\/Messages\/NAVADMIN\/NAV2024\/NAV24044.txt"},"045\/23":{"dl_date":1676600350,"dl_url":"https:\/\/www.mynavyhr.navy.mil\/Portals\/55\/Messages\/NAVADMIN\/NAV2023\/NAV23045.txt"},"045\/24":{"dl_date":1709758949,"dl_url":"https:\/\/www.mynavyhr.navy.mil\/Portals\/55\/Messages\/NAVADMIN\/NAV2024\/NAV24045.txt"},"046\/23":{"dl_date":1676829496,"dl_url":"https:\/\/www.mynavyhr.navy.mil\/Portals\/55\/Messages\/NAVADMIN\/NAV2023\/NAV23046.txt"},"046\/24":{"dl_date":1710189579,"dl_url":"https:\/\/www.mynavyhr.navy.mil\/Portals\/55\/Messages\/NAVADMIN\/NAV2024\/NAV24046.txt"},"047\/23":{"dl_date":1677024790,"dl_url":"https:\/\/www.mynavyhr.navy.mil\/Portals\/55\/Messages\/NAVADMIN\/NAV2023\/NAV23047.txt"},"047\/24":{"dl_date":1710189579,"dl_url":"https:\/\/www.mynavyhr.navy.mil\/Portals\/55\/Messages\/NAVADMIN\/NAV2024\/NAV24047.txt"},"048\/23":{"dl_date":1677024790,"dl_url":"https:\/\/www.mynavyhr.navy.mil\/Portals\/55\/Messages\/NAVADMIN\/NAV2023\/NAV23048.txt"},"048\/24":{"dl_date":1710189579,"dl_url":"https:\/\/www.mynavyhr.navy.mil\/Portals\/55\/Messages\/NAVADMIN\/NAV2024\/NAV24048.txt"},"049\/23":{"dl_date":1677024790,"dl_url":"https:\/\/www.mynavyhr.navy.mil\/Portals\/55\/Messages\/NAVADMIN\/NAV2023\/NAV23049.txt"},"049\/24":{"dl_date":1710189579,"dl_url":"https:\/\/www.mynavyhr.navy.mil\/Portals\/55\/Messages\/NAVADMIN\/NAV2024\/NAV24049.txt"},"050\/23":{"dl_date":1677024790,"dl_url":"https:\/\/www.mynavyhr.navy.mil\/Portals\/55\/Messages\/NAVADMIN\/NAV2023\/NAV23050.txt"},"050\/24":{"dl_date":1710189579,"dl_url":"https:\/\/www.mynavyhr.navy.mil\/Portals\/55\/Messages\/NAVADMIN\/NAV2024\/NAV24050.txt"},"051\/23":{"dl_date":1677024790,"dl_url":"https:\/\/www.mynavyhr.navy.mil\/Portals\/55\/Messages\/NAVADMIN\/NAV2023\/NAV23051.txt"},"051\/24":{"dl_date":1710286564,"dl_url":"https:\/\/www.mynavyhr.navy.mil\/Portals\/55\/Messages\/NAVADMIN\/NAV2024\/NAV24051.txt"},"052\/23":{"dl_date":1677114159,"dl_url":"https:\/\/www.mynavyhr.navy.mil\/Portals\/55\/Messages\/NAVADMIN\/NAV2023\/NAV23052.txt"},"052\/24":{"dl_date":1710286564,"dl_url":"https:\/\/www.mynavyhr.navy.mil\/Portals\/55\/Messages\/NAVADMIN\/NAV2024\/NAV24052.txt"},"053\/23":{"dl_date":1677290385,"dl_url":"https:\/\/www.mynavyhr.navy.mil\/Portals\/55\/Messages\/NAVADMIN\/NAV2023\/NAV23053.txt"},"053\/24":{"dl_date":1710537881,"dl_url":"https:\/\/www.mynavyhr.navy.mil\/Portals\/55\/Messages\/NAVADMIN\/NAV2024\/NAV24053.txt"},"054\/23":{"dl_date":1677290385,"dl_url":"https:\/\/www.mynavyhr.navy.mil\/Portals\/55\/Messages\/NAVADMIN\/NAV2023\/NAV23054.txt"},"054\/24":{"dl_date":1710537882,"dl_url":"https:\/\/www.mynavyhr.navy.mil\/Portals\/55\/Messages\/NAVADMIN\/NAV2024\/NAV24054.txt"},"055\/23":{"dl_date":1677805817,"dl_url":"https:\/\/www.mynavyhr.navy.mil\/Portals\/55\/Messages\/NAVADMIN\/NAV2023\/NAV23055.txt"},"055\/24":{"dl_date":1710888343,"dl_url":"https:\/\/www.mynavyhr.navy.mil\/Portals\/55\/Messages\/NAVADMIN\/NAV2024\/NAV24055.txt"},"056\/23":{"dl_date":1677805817,"dl_url":"https:\/\/www.mynavyhr.navy.mil\/Portals\/55\/Messages\/NAVADMIN\/NAV2023\/NAV23056.txt"},"056\/24":{"dl_date":1710888344,"dl_url":"https:\/\/www.mynavyhr.navy.mil\/Portals\/55\/Messages\/NAVADMIN\/NAV2024\/NAV24056.txt"},"057\/23":{"dl_date":1677805817,"dl_url":"https:\/\/www.mynavyhr.navy.mil\/Portals\/55\/Messages\/NAVADMIN\/NAV2023\/NAV23057.txt"},"057\/24":{"dl_date":1710973090,"dl_url":"https:\/\/www.mynavyhr.navy.mil\/Portals\/55\/Messages\/NAVADMIN\/NAV2024\/NAV24057.txt"},"058\/23":{"dl_date":1677805817,"dl_url":"https:\/\/www.mynavyhr.navy.mil\/Portals\/55\/Messages\/NAVADMIN\/NAV2023\/NAV23058.txt"},"058\/24":{"dl_date":1711058034,"dl_url":"https:\/\/www.mynavyhr.navy.mil\/Portals\/55\/Messages\/NAVADMIN\/NAV2024\/NAV24058.txt"},"059\/23":{"dl_date":1677805817,"dl_url":"https:\/\/www.mynavyhr.navy.mil\/Portals\/55\/Messages\/NAVADMIN\/NAV2023\/NAV23059.txt"},"059\/24":{"dl_date":1711058034,"dl_url":"https:\/\/www.mynavyhr.navy.mil\/Portals\/55\/Messages\/NAVADMIN\/NAV2024\/NAV24059.txt"},"060\/23":{"dl_date":1677805817,"dl_url":"https:\/\/www.mynavyhr.navy.mil\/Portals\/55\/Messages\/NAVADMIN\/NAV2023\/NAV23060.txt"},"060\/24":{"dl_date":1711659787,"dl_url":"https:\/\/www.mynavyhr.navy.mil\/Portals\/55\/Messages\/NAVADMIN\/NAV2024\/NAV24060.txt"},"061\/23":{"dl_date":1677805817,"dl_url":"https:\/\/www.mynavyhr.navy.mil\/Portals\/55\/Messages\/NAVADMIN\/NAV2023\/NAV23061.txt"},"061\/24":{"dl_date":1711659787,"dl_url":"https:\/\/www.mynavyhr.navy.mil\/Portals\/55\/Messages\/NAVADMIN\/NAV2024\/NAV24061.txt"},"062\/23":{"dl_date":1677805816,"dl_url":"https:\/\/www.mynavyhr.navy.mil\/Portals\/55\/Messages\/NAVADMIN\/NAV2023\/NAV23062.txt"},"062\/24":{"dl_date":1711659788,"dl_url":"https:\/\/www.mynavyhr.navy.mil\/Portals\/55\/Messages\/NAVADMIN\/NAV2024\/NAV24062.txt?ver=s7f2IHrZOyoG95G5SapjxA%3d%3d"},"063\/23":{"dl_date":1677895444,"dl_url":"https:\/\/www.mynavyhr.navy.mil\/Portals\/55\/Messages\/NAVADMIN\/NAV2023\/NAV23063.txt"},"063\/24":{"dl_date":1711659787,"dl_url":"https:\/\/www.mynavyhr.navy.mil\/Portals\/55\/Messages\/NAVADMIN\/NAV2024\/NAV24063.txt"},"064\/23":{"dl_date":1677895443,"dl_url":"https:\/\/www.mynavyhr.navy.mil\/Portals\/55\/Messages\/NAVADMIN\/NAV2023\/NAV23064.txt"},"064\/24":{"dl_date":1711659788,"dl_url":"https:\/\/www.mynavyhr.navy.mil\/Portals\/55\/Messages\/NAVADMIN\/NAV2024\/NAV24064.txt?ver=qA2pZN3avVLfLhfk8oth_A%3d%3d"},"065\/23":{"dl_date":1678317272,"dl_url":"https:\/\/www.mynavyhr.navy.mil\/Portals\/55\/Messages\/NAVADMIN\/NAV2023\/NAV23065.txt"},"065\/24":{"dl_date":1715898921,"dl_url":"https:\/\/www.mynavyhr.navy.mil\/Portals\/55\/Messages\/NAVADMIN\/NAV2024\/NAV24065.txt"},"066\/23":{"dl_date":1678317272,"dl_url":"https:\/\/www.mynavyhr.navy.mil\/Portals\/55\/Messages\/NAVADMIN\/NAV2023\/NAV23066.txt"},"066\/24":{"dl_date":1711748158,"dl_url":"https:\/\/www.mynavyhr.navy.mil\/Portals\/55\/Messages\/NAVADMIN\/NAV2024\/NAV24066.txt"},"067\/23":{"dl_date":1678746501,"dl_url":"https:\/\/www.mynavyhr.navy.mil\/Portals\/55\/Messages\/NAVADMIN\/NAV2023\/NAV23067.txt"},"067\/24":{"dl_date":1711748158,"dl_url":"https:\/\/www.mynavyhr.navy.mil\/Portals\/55\/Messages\/NAVADMIN\/NAV2024\/NAV24067.txt"},"068\/23":{"dl_date":1678916896,"dl_url":"https:\/\/www.mynavyhr.navy.mil\/Portals\/55\/Messages\/NAVADMIN\/NAV2023\/NAV23068.txt"},"068\/24":{"dl_date":1712006610,"dl_url":"https:\/\/www.mynavyhr.navy.mil\/Portals\/55\/Messages\/NAVADMIN\/NAV2024\/NAV24068.txt"},"069\/23":{"dl_date":1678916896,"dl_url":"https:\/\/www.mynavyhr.navy.mil\/Portals\/55\/Messages\/NAVADMIN\/NAV2023\/NAV23069.txt"},"069\/24":{"dl_date":1712184324,"dl_url":"https:\/\/www.mynavyhr.navy.mil\/Portals\/55\/Messages\/NAVADMIN\/NAV2024\/NAV24069.txt"},"070\/23":{"dl_date":1678916895,"dl_url":"https:\/\/www.mynavyhr.navy.mil\/Portals\/55\/Messages\/NAVADMIN\/NAV2023\/NAV23070.txt"},"070\/24":{"dl_date":1712351081,"dl_url":"https:\/\/www.mynavyhr.navy.mil\/Portals\/55\/Messages\/NAVADMIN\/NAV2024\/NAV24070.txt"},"071\/23":{"dl_date":1678916895,"dl_url":"https:\/\/www.mynavyhr.navy.mil\/Portals\/55\/Messages\/NAVADMIN\/NAV2023\/NAV23071.txt"},"071\/24":{"dl_date":1712351081,"dl_url":"https:\/\/www.mynavyhr.navy.mil\/Portals\/55\/Messages\/NAVADMIN\/NAV2024\/NAV24071.txt"},"072\/23":{"dl_date":1679091183,"dl_url":"https:\/\/www.mynavyhr.navy.mil\/Portals\/55\/Messages\/NAVADMIN\/NAV2023\/NAV23072.txt"},"072\/24":{"dl_date":1714517357,"dl_url":"https:\/\/www.mynavyhr.navy.mil\/Portals\/55\/Messages\/NAVADMIN\/NAV2024\/NAV24072.txt"},"073\/23":{"dl_date":1679091183,"dl_url":"https:\/\/www.mynavyhr.navy.mil\/Portals\/55\/Messages\/NAVADMIN\/NAV2023\/NAV23073.txt"},"073\/24":{"dl_date":1714517357,"dl_url":"https:\/\/www.mynavyhr.navy.mil\/Portals\/55\/Messages\/NAVADMIN\/NAV2024\/NAV24073.txt"},"074\/23":{"dl_date":1679091183,"dl_url":"https:\/\/www.mynavyhr.navy.mil\/Portals\/55\/Messages\/NAVADMIN\/NAV2023\/NAV23074.txt"},"074\/24":{"dl_date":1714517357,"dl_url":"https:\/\/www.mynavyhr.navy.mil\/Portals\/55\/Messages\/NAVADMIN\/NAV2024\/NAV24074.txt"},"075\/23":{"dl_date":1679751858,"dl_url":"https:\/\/www.mynavyhr.navy.mil\/Portals\/55\/Messages\/NAVADMIN\/NAV2023\/NAV23075.txt"},"075\/24":{"dl_date":1715898920,"dl_url":"https:\/\/www.mynavyhr.navy.mil\/Portals\/55\/Messages\/NAVADMIN\/NAV2024\/NAV24075.txt"},"076\/23":{"dl_date":1679751858,"dl_url":"https:\/\/www.mynavyhr.navy.mil\/Portals\/55\/Messages\/NAVADMIN\/NAV2023\/NAV23076.txt"},"076\/24":{"dl_date":1715031700,"dl_url":"https:\/\/www.mynavyhr.navy.mil\/Portals\/55\/Messages\/NAVADMIN\/NAV2024\/NAV24076.txt"},"077\/23":{"dl_date":1680043777,"dl_url":"https:\/\/www.mynavyhr.navy.mil\/Portals\/55\/Messages\/NAVADMIN\/NAV2023\/NAV23077.txt"},"077\/24":{"dl_date":1714517356,"dl_url":"https:\/\/www.mynavyhr.navy.mil\/Portals\/55\/Messages\/NAVADMIN\/NAV2024\/NAV24077.txt"},"078\/23":{"dl_date":1680043777,"dl_url":"https:\/\/www.mynavyhr.navy.mil\/Portals\/55\/Messages\/NAVADMIN\/NAV2023\/NAV23078.txt"},"078\/24":{"dl_date":1714517357,"dl_url":"https:\/\/www.mynavyhr.navy.mil\/Portals\/55\/Messages\/NAVADMIN\/NAV2024\/NAV24078.txt"},"078\/95":{"dl_date":1735748920,"dl_url":"https:\/\/www.mynavyhr.navy.mil\/Portals\/55\/Messages\/NAVADMIN\/NAV95078.txt.txt"},"079\/23":{"dl_date":1680043776,"dl_url":"https:\/\/www.mynavyhr.navy.mil\/Portals\/55\/Messages\/NAVADMIN\/NAV2023\/NAV23079.txt"},"079\/24":{"dl_date":1713738089,"dl_url":"https:\/\/www.mynavyhr.navy.mil\/Portals\/55\/Messages\/NAVADMIN\/NAV2024\/NAV24079.txt"},"080\/23":{"dl_date":1680295429,"dl_url":"https:\/\/www.mynavyhr.navy.mil\/Portals\/55\/Messages\/NAVADMIN\/NAV2023\/NAV23080.txt"},"080\/24":{"dl_date":1713819884,"dl_url":"https:\/\/www.mynavyhr.navy.mil\/Portals\/55\/Messages\/NAVADMIN\/NAV2024\/NAV24080.txt"},"081\/23":{"dl_date":1680295429,"dl_url":"https:\/\/www.mynavyhr.navy.mil\/Portals\/55\/Messages\/NAVADMIN\/NAV2023\/NAV23081.txt"},"081\/24":{"dl_date":1713819884,"dl_url":"https:\/\/www.mynavyhr.navy.mil\/Portals\/55\/Messages\/NAVADMIN\/NAV2024\/NAV24081.txt"},"082\/23":{"dl_date":1680295429,"dl_url":"https:\/\/www.mynavyhr.navy.mil\/Portals\/55\/Messages\/NAVADMIN\/NAV2023\/NAV23082.txt"},"082\/24":{"dl_date":1714517356,"dl_url":"https:\/\/www.mynavyhr.navy.mil\/Portals\/55\/Messages\/NAVADMIN\/NAV2024\/NAV24082.txt"},"083\/23":{"dl_date":1680739662,"dl_url":"https:\/\/www.mynavyhr.navy.mil\/Portals\/55\/Messages\/NAVADMIN\/NAV2023\/NAV23083.txt"},"083\/24":{"dl_date":1713995601,"dl_url":"https:\/\/www.mynavyhr.navy.mil\/Portals\/55\/Messages\/NAVADMIN\/NAV2024\/NAV24083.txt"},"084\/23":{"dl_date":1681580258,"dl_url":"https:\/\/www.mynavyhr.navy.mil\/Portals\/55\/Messages\/NAVADMIN\/NAV2023\/NAV23084.txt"},"084\/24":{"dl_date":1714161125,"dl_url":"https:\/\/www.mynavyhr.navy.mil\/Portals\/55\/Messages\/NAVADMIN\/NAV2024\/NAV24084.txt"},"085\/23":{"dl_date":1681444329,"dl_url":"https:\/\/www.mynavyhr.navy.mil\/Portals\/55\/Messages\/NAVADMIN\/NAV2023\/NAV23085.txt"},"085\/24":{"dl_date":1714161125,"dl_url":"https:\/\/www.mynavyhr.navy.mil\/Portals\/55\/Messages\/NAVADMIN\/NAV2024\/NAV24085.txt"},"086\/23":{"dl_date":1681856038,"dl_url":"https:\/\/www.mynavyhr.navy.mil\/Portals\/55\/Messages\/NAVADMIN\/NAV2023\/NAV23086.txt"},"086\/24":{"dl_date":1714422813,"dl_url":"https:\/\/www.mynavyhr.navy.mil\/Portals\/55\/Messages\/NAVADMIN\/NAV2024\/NAV24086.txt"},"087\/23":{"dl_date":1681856038,"dl_url":"https:\/\/www.mynavyhr.navy.mil\/Portals\/55\/Messages\/NAVADMIN\/NAV2023\/NAV23087.txt"},"087\/24":{"dl_date":1714422813,"dl_url":"https:\/\/www.mynavyhr.navy.mil\/Portals\/55\/Messages\/NAVADMIN\/NAV2024\/NAV24087.txt"},"088\/23":{"dl_date":1681856038,"dl_url":"https:\/\/www.mynavyhr.navy.mil\/Portals\/55\/Messages\/NAVADMIN\/NAV2023\/NAV23088.txt"},"088\/24":{"dl_date":1714517356,"dl_url":"https:\/\/www.mynavyhr.navy.mil\/Portals\/55\/Messages\/NAVADMIN\/NAV2024\/NAV24088.txt"},"089\/23":{"dl_date":1681949318,"dl_url":"https:\/\/www.mynavyhr.navy.mil\/Portals\/55\/Messages\/NAVADMIN\/NAV2023\/NAV23089.txt"},"089\/24":{"dl_date":1714517356,"dl_url":"https:\/\/www.mynavyhr.navy.mil\/Portals\/55\/Messages\/NAVADMIN\/NAV2024\/NAV24089.txt"},"090\/23":{"dl_date":1682108643,"dl_url":"https:\/\/www.mynavyhr.navy.mil\/Portals\/55\/Messages\/NAVADMIN\/NAV2023\/NAV23090.txt"},"090\/24":{"dl_date":1714517356,"dl_url":"https:\/\/www.mynavyhr.navy.mil\/Portals\/55\/Messages\/NAVADMIN\/NAV2024\/NAV24090.txt"},"091\/23":{"dl_date":1682108643,"dl_url":"https:\/\/www.mynavyhr.navy.mil\/Portals\/55\/Messages\/NAVADMIN\/NAV2023\/NAV23091.txt"},"091\/24":{"dl_date":1714517356,"dl_url":"https:\/\/www.mynavyhr.navy.mil\/Portals\/55\/Messages\/NAVADMIN\/NAV2024\/NAV24091.txt"},"092\/23":{"dl_date":1682108642,"dl_url":"https:\/\/www.mynavyhr.navy.mil\/Portals\/55\/Messages\/NAVADMIN\/NAV2023\/NAV23092.txt"},"092\/24":{"dl_date":1714676402,"dl_url":"https:\/\/www.mynavyhr.navy.mil\/Portals\/55\/Messages\/NAVADMIN\/NAV2024\/NAV24092.txt"},"093\/23":{"dl_date":1682108642,"dl_url":"https:\/\/www.mynavyhr.navy.mil\/Portals\/55\/Messages\/NAVADMIN\/NAV2023\/NAV23093.txt"},"093\/24":{"dl_date":1715031698,"dl_url":"https:\/\/www.mynavyhr.navy.mil\/Portals\/55\/Messages\/NAVADMIN\/NAV2024\/NAV24093.txt"},"094\/23":{"dl_date":1682108642,"dl_url":"https:\/\/www.mynavyhr.navy.mil\/Portals\/55\/Messages\/NAVADMIN\/NAV2023\/NAV23094.txt"},"094\/24":{"dl_date":1715205885,"dl_url":"https:\/\/www.mynavyhr.navy.mil\/Portals\/55\/Messages\/NAVADMIN\/NAV2024\/NAV24094.txt"},"095\/23":{"dl_date":1682547786,"dl_url":"https:\/\/www.mynavyhr.navy.mil\/Portals\/55\/Messages\/NAVADMIN\/NAV2023\/NAV23095.txt"},"095\/24":{"dl_date":1715205883,"dl_url":"https:\/\/www.mynavyhr.navy.mil\/Portals\/55\/Messages\/NAVADMIN\/NAV2024\/NAV24095.txt"},"096\/23":{"dl_date":1682547786,"dl_url":"https:\/\/www.mynavyhr.navy.mil\/Portals\/55\/Messages\/NAVADMIN\/NAV2023\/NAV23096.txt"},"096\/24":{"dl_date":1715726361,"dl_url":"https:\/\/www.mynavyhr.navy.mil\/Portals\/55\/Messages\/NAVADMIN\/NAV2024\/NAV24096.txt"},"097\/23":{"dl_date":1682648882,"dl_url":"https:\/\/www.mynavyhr.navy.mil\/Portals\/55\/Messages\/NAVADMIN\/NAV2023\/NAV23097.txt"},"097\/24":{"dl_date":1715726361,"dl_url":"https:\/\/www.mynavyhr.navy.mil\/Portals\/55\/Messages\/NAVADMIN\/NAV2024\/NAV24097.txt"},"098\/23":{"dl_date":1682727466,"dl_url":"https:\/\/www.mynavyhr.navy.mil\/Portals\/55\/Messages\/NAVADMIN\/NAV2023\/NAV23098.txt"},"098\/24":{"dl_date":1715898918,"dl_url":"https:\/\/www.mynavyhr.navy.mil\/Portals\/55\/Messages\/NAVADMIN\/NAV2024\/NAV24098.txt"},"099\/23":{"dl_date":1682727466,"dl_url":"https:\/\/www.mynavyhr.navy.mil\/Portals\/55\/Messages\/NAVADMIN\/NAV2023\/NAV23099.txt"},"099\/24":{"dl_date":1715992362,"dl_url":"https:\/\/www.mynavyhr.navy.mil\/Portals\/55\/Messages\/NAVADMIN\/NAV2024\/NAV24099.txt"},"100\/23":{"dl_date":1683149200,"dl_url":"https:\/\/www.mynavyhr.navy.mil\/Portals\/55\/Messages\/NAVADMIN\/NAV2023\/NAV23100.txt"},"100\/24":{"dl_date":1716433125,"dl_url":"https:\/\/www.mynavyhr.navy.mil\/Portals\/55\/Messages\/NAVADMIN\/NAV2024\/NAV24100.txt"},"101\/10":{"dl_date":1735748920,"dl_url":"https:\/\/www.mynavyhr.navy.mil\/Portals\/55\/Messages\/NAVADMIN\/NAV2010\/NAV10101.txt"},"101\/24":{"dl_date":1716433125,"dl_url":"https:\/\/www.mynavyhr.navy.mil\/Portals\/55\/Messages\/NAVADMIN\/NAV2024\/NAV24101.txt"},"102\/24":{"dl_date":1716554776,"dl_url":"https:\/\/www.mynavyhr.navy.mil\/Portals\/55\/Messages\/NAVADMIN\/NAV2024\/NAV24102.txt?ver=bOFySCLeIDSG4vgHhZfNAw%3d%3d"},"103\/23":{"dl_date":1683149199,"dl_url":"https:\/\/www.mynavyhr.navy.mil\/Portals\/55\/Messages\/NAVADMIN\/NAV2023\/NAV23103.txt"},"103\/24":{"dl_date":1716554775,"dl_url":"https:\/\/www.mynavyhr.navy.mil\/Portals\/55\/Messages\/NAVADMIN\/NAV2024\/NAV24103.txt"},"104\/23":{"dl_date":1683240515,"dl_url":"https:\/\/www.mynavyhr.navy.mil\/Portals\/55\/Messages\/NAVADMIN\/NAV2023\/NAV23104.txt"},"104\/24":{"dl_date":1716554776,"dl_url":"https:\/\/www.mynavyhr.navy.mil\/Portals\/55\/Messages\/NAVADMIN\/NAV2024\/NAV24104.txt?ver=M2f-Dxf5xtoysCYMsGbngQ%3d%3d"},"105\/23":{"dl_date":1683379045,"dl_url":"https:\/\/www.mynavyhr.navy.mil\/Portals\/55\/Messages\/NAVADMIN\/NAV2023\/NAV23105.txt"},"105\/24":{"dl_date":1718229280,"dl_url":"https:\/\/www.mynavyhr.navy.mil\/Portals\/55\/Messages\/NAVADMIN\/NAV2024\/NAV24105.txt"},"106\/23":{"dl_date":1683583990,"dl_url":"https:\/\/www.mynavyhr.navy.mil\/Portals\/55\/Messages\/NAVADMIN\/NAV2023\/NAV23106.txt"},"106\/24":{"dl_date":1717021970,"dl_url":"https:\/\/www.mynavyhr.navy.mil\/Portals\/55\/Messages\/NAVADMIN\/NAV2024\/NAV24106.txt"},"107\/23":{"dl_date":1683583990,"dl_url":"https:\/\/www.mynavyhr.navy.mil\/Portals\/55\/Messages\/NAVADMIN\/NAV2023\/NAV23107.txt"},"107\/24":{"dl_date":1717102036,"dl_url":"https:\/\/www.mynavyhr.navy.mil\/Portals\/55\/Messages\/NAVADMIN\/NAV2024\/NAV24107.txt"},"108\/23":{"dl_date":1683769822,"dl_url":"https:\/\/www.mynavyhr.navy.mil\/Portals\/55\/Messages\/NAVADMIN\/NAV2023\/NAV23108.txt"},"108\/24":{"dl_date":1717247088,"dl_url":"https:\/\/www.mynavyhr.navy.mil\/Portals\/55\/Messages\/NAVADMIN\/NAV2024\/NAV24108.txt"},"109\/23":{"dl_date":1683769822,"dl_url":"https:\/\/www.mynavyhr.navy.mil\/Portals\/55\/Messages\/NAVADMIN\/NAV2023\/NAV23109.txt"},"109\/24":{"dl_date":1717247088,"dl_url":"https:\/\/www.mynavyhr.navy.mil\/Portals\/55\/Messages\/NAVADMIN\/NAV2024\/NAV24109.txt"},"109\/92":{"dl_date":1735748920,"dl_url":"https:\/\/www.mynavyhr.navy.mil\/Portals\/55\/Messages\/NAVADMIN\/NAV92109.txt.txt"},"110\/23":{"dl_date":1684194676,"dl_url":"https:\/\/www.mynavyhr.navy.mil\/Portals\/55\/Messages\/NAVADMIN\/NAV2023\/NAV23110.txt"},"110\/24":{"dl_date":1717456329,"dl_url":"https:\/\/www.mynavyhr.navy.mil\/Portals\/55\/Messages\/NAVADMIN\/NAV2024\/NAV24110.txt"},"111\/23":{"dl_date":1684194676,"dl_url":"https:\/\/www.mynavyhr.navy.mil\/Portals\/55\/Messages\/NAVADMIN\/NAV2023\/NAV23111.txt"},"111\/24":{"dl_date":1717456329,"dl_url":"https:\/\/www.mynavyhr.navy.mil\/Portals\/55\/Messages\/NAVADMIN\/NAV2024\/NAV24111.txt"},"112\/23":{"dl_date":1684194676,"dl_url":"https:\/\/www.mynavyhr.navy.mil\/Portals\/55\/Messages\/NAVADMIN\/NAV2023\/NAV23112.txt"},"112\/24":{"dl_date":1718229280,"dl_url":"https:\/\/www.mynavyhr.navy.mil\/Portals\/55\/Messages\/NAVADMIN\/NAV2024\/NAV24112.txt"},"113\/23":{"dl_date":1684281318,"dl_url":"https:\/\/www.mynavyhr.navy.mil\/Portals\/55\/Messages\/NAVADMIN\/NAV2023\/NAV23113.txt"},"113\/24":{"dl_date":1717541306,"dl_url":"https:\/\/www.mynavyhr.navy.mil\/Portals\/55\/Messages\/NAVADMIN\/NAV2024\/NAV24113.txt"},"114\/23":{"dl_date":1684453021,"dl_url":"https:\/\/www.mynavyhr.navy.mil\/Portals\/55\/Messages\/NAVADMIN\/NAV2023\/NAV23114.txt"},"114\/24":{"dl_date":1717541306,"dl_url":"https:\/\/www.mynavyhr.navy.mil\/Portals\/55\/Messages\/NAVADMIN\/NAV2024\/NAV24114.txt"},"115\/23":{"dl_date":1684281318,"dl_url":"https:\/\/www.mynavyhr.navy.mil\/Portals\/55\/Messages\/NAVADMIN\/NAV2023\/NAV23115.txt"},"115\/24":{"dl_date":1717541306,"dl_url":"https:\/\/www.mynavyhr.navy.mil\/Portals\/55\/Messages\/NAVADMIN\/NAV2024\/NAV24115.txt"},"116\/23":{"dl_date":1684453021,"dl_url":"https:\/\/www.mynavyhr.navy.mil\/Portals\/55\/Messages\/NAVADMIN\/NAV2023\/NAV23116.txt"},"116\/24":{"dl_date":1717541306,"dl_url":"https:\/\/www.mynavyhr.navy.mil\/Portals\/55\/Messages\/NAVADMIN\/NAV2024\/NAV24116.txt"},"117\/23":{"dl_date":1684453021,"dl_url":"https:\/\/www.mynavyhr.navy.mil\/Portals\/55\/Messages\/NAVADMIN\/NAV2023\/NAV23117.txt"},"117\/24":{"dl_date":1717626564,"dl_url":"https:\/\/www.mynavyhr.navy.mil\/Portals\/55\/Messages\/NAVADMIN\/NAV2024\/NAV24117.txt"},"118\/23":{"dl_date":1684535887,"dl_url":"https:\/\/www.mynavyhr.navy.mil\/Portals\/55\/Messages\/NAVADMIN\/NAV2023\/NAV23118.txt"},"118\/24":{"dl_date":1718144527,"dl_url":"https:\/\/www.mynavyhr.navy.mil\/Portals\/55\/Messages\/NAVADMIN\/NAV2024\/NAV24118.txt"},"119\/23":{"dl_date":1684880940,"dl_url":"https:\/\/www.mynavyhr.navy.mil\/Portals\/55\/Messages\/NAVADMIN\/NAV2023\/NAV23119.txt"},"119\/24":{"dl_date":1718229279,"dl_url":"https:\/\/www.mynavyhr.navy.mil\/Portals\/55\/Messages\/NAVADMIN\/NAV2024\/NAV24119.txt"},"120\/23":{"dl_date":1684802457,"dl_url":"https:\/\/www.mynavyhr.navy.mil\/Portals\/55\/Messages\/NAVADMIN\/NAV2023\/NAV23120.txt"},"120\/24":{"dl_date":1718555338,"dl_url":"https:\/\/www.mynavyhr.navy.mil\/Portals\/55\/Messages\/NAVADMIN\/NAV2024\/NAV24120.txt"},"121\/23":{"dl_date":1684802456,"dl_url":"https:\/\/www.mynavyhr.navy.mil\/Portals\/55\/Messages\/NAVADMIN\/NAV2023\/NAV23121.txt"},"121\/24":{"dl_date":1718752064,"dl_url":"https:\/\/www.mynavyhr.navy.mil\/Portals\/55\/Messages\/NAVADMIN\/NAV2024\/NAV24121.txt"},"122\/23":{"dl_date":1684802456,"dl_url":"https:\/\/www.mynavyhr.navy.mil\/Portals\/55\/Messages\/NAVADMIN\/NAV2023\/NAV23122.txt"},"122\/24":{"dl_date":1718752064,"dl_url":"https:\/\/www.mynavyhr.navy.mil\/Portals\/55\/Messages\/NAVADMIN\/NAV2024\/NAV24122.txt"},"123\/23":{"dl_date":1684880938,"dl_url":"https:\/\/www.mynavyhr.navy.mil\/Portals\/55\/Messages\/NAVADMIN\/NAV2023\/NAV23123.txt"},"123\/24":{"dl_date":1719016178,"dl_url":"https:\/\/www.mynavyhr.navy.mil\/Portals\/55\/Messages\/NAVADMIN\/NAV2024\/NAV24123.txt"},"123\/93":{"dl_date":1735748920,"dl_url":"https:\/\/www.mynavyhr.navy.mil\/Portals\/55\/Messages\/NAVADMIN\/NAV93123.txt"},"124\/23":{"dl_date":1684969667,"dl_url":"https:\/\/www.mynavyhr.navy.mil\/Portals\/55\/Messages\/NAVADMIN\/NAV2023\/NAV23124.txt"},"124\/24":{"dl_date":1719016178,"dl_url":"https:\/\/www.mynavyhr.navy.mil\/Portals\/55\/Messages\/NAVADMIN\/NAV2024\/NAV24124.txt"},"125\/23":{"dl_date":1684969667,"dl_url":"https:\/\/www.mynavyhr.navy.mil\/Portals\/55\/Messages\/NAVADMIN\/NAV2023\/NAV23125.txt"},"125\/24":{"dl_date":1719016178,"dl_url":"https:\/\/www.mynavyhr.navy.mil\/Portals\/55\/Messages\/NAVADMIN\/NAV2024\/NAV24125.txt"},"126\/23":{"dl_date":1684969667,"dl_url":"https:\/\/www.mynavyhr.navy.mil\/Portals\/55\/Messages\/NAVADMIN\/NAV2023\/NAV23126.txt"},"126\/24":{"dl_date":1719269189,"dl_url":"https:\/\/www.mynavyhr.navy.mil\/Portals\/55\/Messages\/NAVADMIN\/NAV2024\/NAV24126.txt"},"127\/23":{"dl_date":1685231729,"dl_url":"https:\/\/www.mynavyhr.navy.mil\/Portals\/55\/Messages\/NAVADMIN\/NAV2023\/NAV23127.txt"},"127\/24":{"dl_date":1719965184,"dl_url":"https:\/\/www.mynavyhr.navy.mil\/Portals\/55\/Messages\/NAVADMIN\/NAV2024\/NAV24127.txt"},"128\/23":{"dl_date":1685231729,"dl_url":"https:\/\/www.mynavyhr.navy.mil\/Portals\/55\/Messages\/NAVADMIN\/NAV2023\/NAV23128.txt"},"128\/24":{"dl_date":1719667556,"dl_url":"https:\/\/www.mynavyhr.navy.mil\/Portals\/55\/Messages\/NAVADMIN\/NAV2024\/NAV24128.txt"},"129\/23":{"dl_date":1685488182,"dl_url":"https:\/\/www.mynavyhr.navy.mil\/Portals\/55\/Messages\/NAVADMIN\/NAV2023\/NAV23129.txt"},"129\/24":{"dl_date":1719610861,"dl_url":"https:\/\/www.mynavyhr.navy.mil\/Portals\/55\/Messages\/NAVADMIN\/NAV2024\/NAV24129.txt"},"130\/23":{"dl_date":1685488182,"dl_url":"https:\/\/www.mynavyhr.navy.mil\/Portals\/55\/Messages\/NAVADMIN\/NAV2023\/NAV23130.txt"},"130\/24":{"dl_date":1719965184,"dl_url":"https:\/\/www.mynavyhr.navy.mil\/Portals\/55\/Messages\/NAVADMIN\/NAV2024\/NAV24130.txt"},"131\/23":{"dl_date":1685578418,"dl_url":"https:\/\/www.mynavyhr.navy.mil\/Portals\/55\/Messages\/NAVADMIN\/NAV2023\/NAV23131.txt"},"131\/24":{"dl_date":1719965184,"dl_url":"https:\/\/www.mynavyhr.navy.mil\/Portals\/55\/Messages\/NAVADMIN\/NAV2024\/NAV24131.txt"},"132\/23":{"dl_date":1685673413,"dl_url":"https:\/\/www.mynavyhr.navy.mil\/Portals\/55\/Messages\/NAVADMIN\/NAV2023\/NAV23132.txt"},"132\/24":{"dl_date":1720042911,"dl_url":"https:\/\/www.mynavyhr.navy.mil\/Portals\/55\/Messages\/NAVADMIN\/NAV2024\/NAV24132.txt"},"133\/23":{"dl_date":1685831186,"dl_url":"https:\/\/www.mynavyhr.navy.mil\/Portals\/55\/Messages\/NAVADMIN\/NAV2023\/NAV23133.txt"},"133\/24":{"dl_date":1720042911,"dl_url":"https:\/\/www.mynavyhr.navy.mil\/Portals\/55\/Messages\/NAVADMIN\/NAV2024\/NAV24133.txt"},"134\/23":{"dl_date":1685831185,"dl_url":"https:\/\/www.mynavyhr.navy.mil\/Portals\/55\/Messages\/NAVADMIN\/NAV2023\/NAV23134.txt"},"134\/24":{"dl_date":1720042911,"dl_url":"https:\/\/www.mynavyhr.navy.mil\/Portals\/55\/Messages\/NAVADMIN\/NAV2024\/NAV24134.txt"},"135\/24":{"dl_date":1720042911,"dl_url":"https:\/\/www.mynavyhr.navy.mil\/Portals\/55\/Messages\/NAVADMIN\/NAV2024\/NAV24135.txt"},"136\/23":{"dl_date":1686181107,"dl_url":"https:\/\/www.mynavyhr.navy.mil\/Portals\/55\/Messages\/NAVADMIN\/NAV2023\/NAV23136.txt"},"136\/24":{"dl_date":1723913088,"dl_url":"https:\/\/www.mynavyhr.navy.mil\/Portals\/55\/Messages\/NAVADMIN\/NAV2024\/NAV24136.txt"},"137\/23":{"dl_date":1686181106,"dl_url":"https:\/\/www.mynavyhr.navy.mil\/Portals\/55\/Messages\/NAVADMIN\/NAV2023\/NAV23137.txt"},"137\/24":{"dl_date":1720479917,"dl_url":"https:\/\/www.mynavyhr.navy.mil\/Portals\/55\/Messages\/NAVADMIN\/NAV2024\/NAV24137.txt"},"138\/24":{"dl_date":1720479915,"dl_url":"https:\/\/www.mynavyhr.navy.mil\/Portals\/55\/Messages\/NAVADMIN\/NAV2024\/NAV24138.txt"},"139\/23":{"dl_date":1686962942,"dl_url":"https:\/\/www.mynavyhr.navy.mil\/Portals\/55\/Messages\/NAVADMIN\/NAV2023\/NAV23139.txt"},"139\/24":{"dl_date":1723913088,"dl_url":"https:\/\/www.mynavyhr.navy.mil\/Portals\/55\/Messages\/NAVADMIN\/NAV2024\/NAV24139.txt"},"140\/23":{"dl_date":1687707871,"dl_url":"https:\/\/www.mynavyhr.navy.mil\/Portals\/55\/Messages\/NAVADMIN\/NAV2023\/NAV23140-1.txt"},"140\/24":{"dl_date":1720723119,"dl_url":"https:\/\/www.mynavyhr.navy.mil\/Portals\/55\/Messages\/NAVADMIN\/NAV2024\/NAV24140.txt"},"141\/23":{"dl_date":1687913785,"dl_url":"https:\/\/www.mynavyhr.navy.mil\/Portals\/55\/Messages\/NAVADMIN\/NAV2023\/NAV23141.txt","links":[{"text":"Complete the linked survey (fixed link)","url":"https:\/\/usnavy.gov1.qualtrics.com\/jfe\/form\/SV_3mk65UxsLQgMMjI"},{"text":"Read linked Health of the Force report (PDF)","url":"https:\/\/www.mynavyhr.navy.mil\/Portals\/55\/Reference\/Publications\/CY2022_HOF_FINAL_8_Feb_23.pdf?ver=NfT0FRHSJlgEtWk0mE22lQ=="}]},"141\/24":{"dl_date":1721151741,"dl_url":"https:\/\/www.mynavyhr.navy.mil\/Portals\/55\/Messages\/NAVADMIN\/NAV2024\/NAV24141.txt"},"142\/23":{"dl_date":1687912066,"dl_url":"https:\/\/www.mynavyhr.navy.mil\/Portals\/55\/Messages\/NAVADMIN\/NAV2023\/NAV23142.txt"},"142\/24":{"dl_date":1721601485,"dl_url":"https:\/\/www.mynavyhr.navy.mil\/Portals\/55\/Messages\/NAVADMIN\/NAV2024\/NAV24142.txt"},"143\/23":{"dl_date":1687912066,"dl_url":"https:\/\/www.mynavyhr.navy.mil\/Portals\/55\/Messages\/NAVADMIN\/NAV2023\/NAV23143.txt"},"143\/24":{"dl_date":1721601485,"dl_url":"https:\/\/www.mynavyhr.navy.mil\/Portals\/55\/Messages\/NAVADMIN\/NAV2024\/NAV24143.txt"},"144\/23":{"dl_date":1687912066,"dl_url":"https:\/\/www.mynavyhr.navy.mil\/Portals\/55\/Messages\/NAVADMIN\/NAV2023\/NAV23144.txt"},"144\/24":{"dl_date":1721601485,"dl_url":"https:\/\/www.mynavyhr.navy.mil\/Portals\/55\/Messages\/NAVADMIN\/NAV2024\/NAV24144.txt"},"145\/23":{"dl_date":1687912066,"dl_url":"https:\/\/www.mynavyhr.navy.mil\/Portals\/55\/Messages\/NAVADMIN\/NAV2023\/NAV23145.txt"},"145\/24":{"dl_date":1721601485,"dl_url":"https:\/\/www.mynavyhr.navy.mil\/Portals\/55\/Messages\/NAVADMIN\/NAV2024\/NAV24145.txt"},"146\/23":{"dl_date":1687992892,"dl_url":"https:\/\/www.mynavyhr.navy.mil\/Portals\/55\/Messages\/NAVADMIN\/NAV2023\/NAV23146.txt"},"146\/24":{"dl_date":1721862773,"dl_url":"https:\/\/www.mynavyhr.navy.mil\/Portals\/55\/Messages\/NAVADMIN\/NAV2024\/NAV24146.txt"},"147\/23":{"dl_date":1688080404,"dl_url":"https:\/\/www.mynavyhr.navy.mil\/Portals\/55\/Messages\/NAVADMIN\/NAV2023\/NAV23147.txt"},"147\/24":{"dl_date":1721862773,"dl_url":"https:\/\/www.mynavyhr.navy.mil\/Portals\/55\/Messages\/NAVADMIN\/NAV2024\/NAV24147.txt"},"148\/23":{"dl_date":1688080404,"dl_url":"https:\/\/www.mynavyhr.navy.mil\/Portals\/55\/Messages\/NAVADMIN\/NAV2023\/NAV23148.txt"},"148\/24":{"dl_date":1722379865,"dl_url":"https:\/\/www.mynavyhr.navy.mil\/Portals\/55\/Messages\/NAVADMIN\/NAV2024\/NAV24148.txt"},"149\/23":{"dl_date":1688165613,"dl_url":"https:\/\/www.mynavyhr.navy.mil\/Portals\/55\/Messages\/NAVADMIN\/NAV2023\/NAV23149.txt"},"149\/24":{"dl_date":1722379865,"dl_url":"https:\/\/www.mynavyhr.navy.mil\/Portals\/55\/Messages\/NAVADMIN\/NAV2024\/NAV24149.txt"},"150\/23":{"dl_date":1688165613,"dl_url":"https:\/\/www.mynavyhr.navy.mil\/Portals\/55\/Messages\/NAVADMIN\/NAV2023\/NAV23150.txt"},"150\/24":{"dl_date":1722460200,"dl_url":"https:\/\/www.mynavyhr.navy.mil\/Portals\/55\/Messages\/NAVADMIN\/NAV2024\/NAV24150.txt"},"151\/23":{"dl_date":1688165613,"dl_url":"https:\/\/www.mynavyhr.navy.mil\/Portals\/55\/Messages\/NAVADMIN\/NAV2023\/NAV23151.txt"},"151\/24":{"dl_date":1722560944,"dl_url":"https:\/\/www.mynavyhr.navy.mil\/Portals\/55\/Messages\/NAVADMIN\/NAV2024\/NAV24151.txt"},"152\/23":{"dl_date":1688165612,"dl_url":"https:\/\/www.mynavyhr.navy.mil\/Portals\/55\/Messages\/NAVADMIN\/NAV2023\/NAV23152.txt"},"152\/24":{"dl_date":1722629523,"dl_url":"https:\/\/www.mynavyhr.navy.mil\/Portals\/55\/Messages\/NAVADMIN\/NAV2024\/NAV24152.txt"},"153\/23":{"dl_date":1689636028,"dl_url":"https:\/\/www.mynavyhr.navy.mil\/Portals\/55\/Messages\/NAVADMIN\/NAV2023\/NAV23153.txt"},"153\/24":{"dl_date":1723145673,"dl_url":"https:\/\/www.mynavyhr.navy.mil\/Portals\/55\/Messages\/NAVADMIN\/NAV2024\/NAV24153.txt"},"154\/23":{"dl_date":1689636028,"dl_url":"https:\/\/www.mynavyhr.navy.mil\/Portals\/55\/Messages\/NAVADMIN\/NAV2023\/NAV23154.txt"},"154\/24":{"dl_date":1723913086,"dl_url":"https:\/\/www.mynavyhr.navy.mil\/Portals\/55\/Messages\/NAVADMIN\/NAV2024\/NAV24154.txt"},"155\/23":{"dl_date":1689636027,"dl_url":"https:\/\/www.mynavyhr.navy.mil\/Portals\/55\/Messages\/NAVADMIN\/NAV2023\/NAV23155.txt"},"155\/24":{"dl_date":1723145673,"dl_url":"https:\/\/www.mynavyhr.navy.mil\/Portals\/55\/Messages\/NAVADMIN\/NAV2024\/NAV24155.txt"},"156\/23":{"dl_date":1689636027,"dl_url":"https:\/\/www.mynavyhr.navy.mil\/Portals\/55\/Messages\/NAVADMIN\/NAV2023\/NAV23156.txt"},"156\/24":{"dl_date":1723218467,"dl_url":"https:\/\/www.mynavyhr.navy.mil\/Portals\/55\/Messages\/NAVADMIN\/NAV2024\/NAV24156.txt"},"157\/23":{"dl_date":1689636027,"dl_url":"https:\/\/www.mynavyhr.navy.mil\/Portals\/55\/Messages\/NAVADMIN\/NAV2023\/NAV23157.txt"},"157\/24":{"dl_date":1723674352,"dl_url":"https:\/\/www.mynavyhr.navy.mil\/Portals\/55\/Messages\/NAVADMIN\/NAV2024\/NAV24157.txt"},"158\/23":{"dl_date":1689723802,"dl_url":"https:\/\/www.mynavyhr.navy.mil\/Portals\/55\/Messages\/NAVADMIN\/NAV2023\/NAV23158.txt"},"158\/24":{"dl_date":1723218468,"dl_url":"https:\/\/www.mynavyhr.navy.mil\/Portals\/55\/Messages\/NAVADMIN\/NAV2024\/NAV24158.txt"},"159\/23":{"dl_date":1689806126,"dl_url":"https:\/\/www.mynavyhr.navy.mil\/Portals\/55\/Messages\/NAVADMIN\/NAV2023\/NAV23159.txt"},"159\/24":{"dl_date":1723766339,"dl_url":"https:\/\/www.mynavyhr.navy.mil\/Portals\/55\/Messages\/NAVADMIN\/NAV2024\/NAV24159.txt"},"160\/23":{"dl_date":1689806126,"dl_url":"https:\/\/www.mynavyhr.navy.mil\/Portals\/55\/Messages\/NAVADMIN\/NAV2023\/NAV23160.txt"},"160\/24":{"dl_date":1723835289,"dl_url":"https:\/\/www.mynavyhr.navy.mil\/Portals\/55\/Messages\/NAVADMIN\/NAV2024\/NAV24160.txt"},"161\/23":{"dl_date":1689886921,"dl_url":"https:\/\/www.mynavyhr.navy.mil\/Portals\/55\/Messages\/NAVADMIN\/NAV2023\/NAV23161.txt"},"161\/24":{"dl_date":1724107576,"dl_url":"https:\/\/www.mynavyhr.navy.mil\/Portals\/55\/Messages\/NAVADMIN\/NAV2024\/NAV24161.txt"},"162\/23":{"dl_date":1690070088,"dl_url":"https:\/\/www.mynavyhr.navy.mil\/Portals\/55\/Messages\/NAVADMIN\/NAV2023\/NAV23162.txt"},"162\/24":{"dl_date":1724107576,"dl_url":"https:\/\/www.mynavyhr.navy.mil\/Portals\/55\/Messages\/NAVADMIN\/NAV2024\/NAV24162.txt"},"163\/23":{"dl_date":1690509848,"dl_url":"https:\/\/www.mynavyhr.navy.mil\/Portals\/55\/Messages\/NAVADMIN\/NAV2023\/NAV23163.txt"},"163\/24":{"dl_date":1724107576,"dl_url":"https:\/\/www.mynavyhr.navy.mil\/Portals\/55\/Messages\/NAVADMIN\/NAV2024\/NAV24163.txt"},"164\/23":{"dl_date":1690509848,"dl_url":"https:\/\/www.mynavyhr.navy.mil\/Portals\/55\/Messages\/NAVADMIN\/NAV2023\/NAV23164.txt"},"164\/24":{"dl_date":1724107575,"dl_url":"https:\/\/www.mynavyhr.navy.mil\/Portals\/55\/Messages\/NAVADMIN\/NAV2024\/NAV24164.txt"},"165\/23":{"dl_date":1690509847,"dl_url":"https:\/\/www.mynavyhr.navy.mil\/Portals\/55\/Messages\/NAVADMIN\/NAV2023\/NAV23165.txt"},"165\/24":{"dl_date":1724107575,"dl_url":"https:\/\/www.mynavyhr.navy.mil\/Portals\/55\/Messages\/NAVADMIN\/NAV2024\/NAV24165.txt"},"166\/23":{"dl_date":1690509847,"dl_url":"https:\/\/www.mynavyhr.navy.mil\/Portals\/55\/Messages\/NAVADMIN\/NAV2023\/NAV23166.txt"},"166\/24":{"dl_date":1727303756,"dl_url":"https:\/\/www.mynavyhr.navy.mil\/Portals\/55\/Messages\/NAVADMIN\/NAV2024\/NAV24166.txt"},"167\/23":{"dl_date":1690571129,"dl_url":"https:\/\/www.mynavyhr.navy.mil\/Portals\/55\/Messages\/NAVADMIN\/NAV2023\/NAV23167.txt"},"167\/24":{"dl_date":1724107576,"dl_url":"https:\/\/www.mynavyhr.navy.mil\/Portals\/55\/Messages\/NAVADMIN\/NAV2024\/NAV24167.txt"},"168\/23":{"dl_date":1690509847,"dl_url":"https:\/\/www.mynavyhr.navy.mil\/Portals\/55\/Messages\/NAVADMIN\/NAV2023\/NAV23168.txt"},"168\/24":{"dl_date":1724285518,"dl_url":"https:\/\/www.mynavyhr.navy.mil\/Portals\/55\/Messages\/NAVADMIN\/NAV2024\/NAV24168.txt"},"169\/23":{"dl_date":1690571129,"dl_url":"https:\/\/www.mynavyhr.navy.mil\/Portals\/55\/Messages\/NAVADMIN\/NAV2023\/NAV23169.txt"},"169\/24":{"dl_date":1724285518,"dl_url":"https:\/\/www.mynavyhr.navy.mil\/Portals\/55\/Messages\/NAVADMIN\/NAV2024\/NAV24169.txt"},"170\/23":{"dl_date":1691013094,"dl_url":"https:\/\/www.mynavyhr.navy.mil\/Portals\/55\/Messages\/NAVADMIN\/NAV2023\/NAV23170.txt"},"170\/24":{"dl_date":1724285518,"dl_url":"https:\/\/www.mynavyhr.navy.mil\/Portals\/55\/Messages\/NAVADMIN\/NAV2024\/NAV24170.txt"},"171\/23":{"dl_date":1691013094,"dl_url":"https:\/\/www.mynavyhr.navy.mil\/Portals\/55\/Messages\/NAVADMIN\/NAV2023\/NAV23171.txt"},"171\/24":{"dl_date":1724285518,"dl_url":"https:\/\/www.mynavyhr.navy.mil\/Portals\/55\/Messages\/NAVADMIN\/NAV2024\/NAV24171.txt"},"172\/23":{"dl_date":1691013093,"dl_url":"https:\/\/www.mynavyhr.navy.mil\/Portals\/55\/Messages\/NAVADMIN\/NAV2023\/NAV23172.txt"},"172\/24":{"dl_date":1724448863,"dl_url":"https:\/\/www.mynavyhr.navy.mil\/Portals\/55\/Messages\/NAVADMIN\/NAV2024\/NAV24172.txt"},"173\/23":{"dl_date":1691013093,"dl_url":"https:\/\/www.mynavyhr.navy.mil\/Portals\/55\/Messages\/NAVADMIN\/NAV2023\/NAV23173.txt"},"173\/24":{"dl_date":1724885442,"dl_url":"https:\/\/www.mynavyhr.navy.mil\/Portals\/55\/Messages\/NAVADMIN\/NAV2024\/NAV24173.txt"},"174\/23":{"dl_date":1691013093,"dl_url":"https:\/\/www.mynavyhr.navy.mil\/Portals\/55\/Messages\/NAVADMIN\/NAV2023\/NAV23174.txt"},"174\/24":{"dl_date":1724885442,"dl_url":"https:\/\/www.mynavyhr.navy.mil\/Portals\/55\/Messages\/NAVADMIN\/NAV2024\/NAV24174.txt"},"175\/23":{"dl_date":1691013093,"dl_url":"https:\/\/www.mynavyhr.navy.mil\/Portals\/55\/Messages\/NAVADMIN\/NAV2023\/NAV23175.txt"},"175\/24":{"dl_date":1724885442,"dl_url":"https:\/\/www.mynavyhr.navy.mil\/Portals\/55\/Messages\/NAVADMIN\/NAV2024\/NAV24175.txt"},"176\/23":{"dl_date":1691013093,"dl_url":"https:\/\/www.mynavyhr.navy.mil\/Portals\/55\/Messages\/NAVADMIN\/NAV2023\/NAV23176.txt"},"176\/24":{"dl_date":1725408330,"dl_url":"https:\/\/www.mynavyhr.navy.mil\/Portals\/55\/Messages\/NAVADMIN\/NAV2024\/NAV24176.txt"},"177\/23":{"dl_date":1691108629,"dl_url":"https:\/\/www.mynavyhr.navy.mil\/Portals\/55\/Messages\/NAVADMIN\/NAV2023\/NAV23177.txt"},"177\/24":{"dl_date":1725485055,"dl_url":"https:\/\/www.mynavyhr.navy.mil\/Portals\/55\/Messages\/NAVADMIN\/NAV2024\/NAV24177.txt"},"178\/23":{"dl_date":1691108629,"dl_url":"https:\/\/www.mynavyhr.navy.mil\/Portals\/55\/Messages\/NAVADMIN\/NAV2023\/NAV23178.txt"},"178\/24":{"dl_date":1725662989,"dl_url":"https:\/\/www.mynavyhr.navy.mil\/Portals\/55\/Messages\/NAVADMIN\/NAV2024\/NAV24178.txt"},"179\/23":{"dl_date":1691108629,"dl_url":"https:\/\/www.mynavyhr.navy.mil\/Portals\/55\/Messages\/NAVADMIN\/NAV2023\/NAV23179.txt"},"179\/24":{"dl_date":1725662989,"dl_url":"https:\/\/www.mynavyhr.navy.mil\/Portals\/55\/Messages\/NAVADMIN\/NAV2024\/NAV24179.txt"},"180\/23":{"dl_date":1691282731,"dl_url":"https:\/\/www.mynavyhr.navy.mil\/Portals\/55\/Messages\/NAVADMIN\/NAV2023\/NAV23180.txt"},"180\/24":{"dl_date":1725913265,"dl_url":"https:\/\/www.mynavyhr.navy.mil\/Portals\/55\/Messages\/NAVADMIN\/NAV2024\/NAV24180.txt"},"181\/23":{"dl_date":1691448644,"dl_url":"https:\/\/www.mynavyhr.navy.mil\/Portals\/55\/Messages\/NAVADMIN\/NAV2023\/NAV23181.txt"},"181\/24":{"dl_date":1726016284,"dl_url":"https:\/\/www.mynavyhr.navy.mil\/Portals\/55\/Messages\/NAVADMIN\/NAV2024\/NAV24181.txt"},"182\/23":{"dl_date":1691710431,"dl_url":"https:\/\/www.mynavyhr.navy.mil\/Portals\/55\/Messages\/NAVADMIN\/NAV2023\/NAV23182.txt"},"182\/24":{"dl_date":1726179849,"dl_url":"https:\/\/www.mynavyhr.navy.mil\/Portals\/55\/Messages\/NAVADMIN\/NAV2024\/NAV24182.txt"},"183\/23":{"dl_date":1692048752,"dl_url":"https:\/\/www.mynavyhr.navy.mil\/Portals\/55\/Messages\/NAVADMIN\/NAV2023\/NAV23183.txt"},"183\/24":{"dl_date":1733430789,"dl_url":"https:\/\/www.mynavyhr.navy.mil\/Portals\/55\/Messages\/NAVADMIN\/NAV2024\/NAV24183.txt"},"184\/14":{"dl_date":1735748920,"dl_url":"https:\/\/www.mynavyhr.navy.mil\/Portals\/55\/Messages\/NAVADMIN\/NAV2014\/NAV14184.txt"},"184\/23":{"dl_date":1692048752,"dl_url":"https:\/\/www.mynavyhr.navy.mil\/Portals\/55\/Messages\/NAVADMIN\/NAV2023\/NAV23184.txt"},"184\/24":{"dl_date":1733430790,"dl_url":"https:\/\/www.mynavyhr.navy.mil\/Portals\/55\/Messages\/NAVADMIN\/NAV2024\/NAV24184.txt"},"185\/23":{"dl_date":1692048752,"dl_url":"https:\/\/www.mynavyhr.navy.mil\/Portals\/55\/Messages\/NAVADMIN\/NAV2023\/NAV23185.txt"},"185\/24":{"dl_date":1726258366,"dl_url":"https:\/\/www.mynavyhr.navy.mil\/Portals\/55\/Messages\/NAVADMIN\/NAV2024\/NAV24185.txt"},"186\/23":{"dl_date":1692048752,"dl_url":"https:\/\/www.mynavyhr.navy.mil\/Portals\/55\/Messages\/NAVADMIN\/NAV2023\/NAV23186.txt"},"186\/24":{"dl_date":1726525457,"dl_url":"https:\/\/www.mynavyhr.navy.mil\/Portals\/55\/Messages\/NAVADMIN\/NAV2024\/NAV24186.txt"},"187\/23":{"dl_date":1692048751,"dl_url":"https:\/\/www.mynavyhr.navy.mil\/Portals\/55\/Messages\/NAVADMIN\/NAV2023\/NAV23187.txt"},"187\/24":{"dl_date":1726698872,"dl_url":"https:\/\/www.mynavyhr.navy.mil\/Portals\/55\/Messages\/NAVADMIN\/NAV2024\/NAV24187.txt"},"188\/23":{"dl_date":1692048751,"dl_url":"https:\/\/www.mynavyhr.navy.mil\/Portals\/55\/Messages\/NAVADMIN\/NAV2023\/NAV23188.txt"},"188\/24":{"dl_date":1726525457,"dl_url":"https:\/\/www.mynavyhr.navy.mil\/Portals\/55\/Messages\/NAVADMIN\/NAV2024\/NAV24188.txt"},"189\/23":{"dl_date":1692144433,"dl_url":"https:\/\/www.mynavyhr.navy.mil\/Portals\/55\/Messages\/NAVADMIN\/NAV2023\/NAV23189.txt"},"189\/24":{"dl_date":1726525457,"dl_url":"https:\/\/www.mynavyhr.navy.mil\/Portals\/55\/Messages\/NAVADMIN\/NAV2024\/NAV24189.txt"},"190\/23":{"dl_date":1692313480,"dl_url":"https:\/\/www.mynavyhr.navy.mil\/Portals\/55\/Messages\/NAVADMIN\/NAV2023\/NAV23190.txt"},"190\/24":{"dl_date":1726525457,"dl_url":"https:\/\/www.mynavyhr.navy.mil\/Portals\/55\/Messages\/NAVADMIN\/NAV2024\/NAV24190.txt"},"191\/23":{"dl_date":1692313479,"dl_url":"https:\/\/www.mynavyhr.navy.mil\/Portals\/55\/Messages\/NAVADMIN\/NAV2023\/NAV23191.txt"},"191\/24":{"dl_date":1726611028,"dl_url":"https:\/\/www.mynavyhr.navy.mil\/Portals\/55\/Messages\/NAVADMIN\/NAV2024\/NAV24191.txt"},"192\/23":{"dl_date":1692313479,"dl_url":"https:\/\/www.mynavyhr.navy.mil\/Portals\/55\/Messages\/NAVADMIN\/NAV2023\/NAV23192.txt"},"192\/24":{"dl_date":1726698872,"dl_url":"https:\/\/www.mynavyhr.navy.mil\/Portals\/55\/Messages\/NAVADMIN\/NAV2024\/NAV24192.txt"},"193\/22":{"dl_date":1665784423,"dl_url":"https:\/\/www.mynavyhr.navy.mil\/Portals\/55\/Messages\/NAVADMIN\/NAV2022\/NAV22193.txt"},"193\/23":{"dl_date":1692313479,"dl_url":"https:\/\/www.mynavyhr.navy.mil\/Portals\/55\/Messages\/NAVADMIN\/NAV2023\/NAV23193.txt"},"193\/24":{"dl_date":1726698872,"dl_url":"https:\/\/www.mynavyhr.navy.mil\/Portals\/55\/Messages\/NAVADMIN\/NAV2024\/NAV24193.txt"},"194\/23":{"dl_date":1692313478,"dl_url":"https:\/\/www.mynavyhr.navy.mil\/Portals\/55\/Messages\/NAVADMIN\/NAV2023\/NAV23194.txt"},"194\/24":{"dl_date":1726698872,"dl_url":"https:\/\/www.mynavyhr.navy.mil\/Portals\/55\/Messages\/NAVADMIN\/NAV2024\/NAV24194.txt"},"195\/23":{"dl_date":1692313478,"dl_url":"https:\/\/www.mynavyhr.navy.mil\/Portals\/55\/Messages\/NAVADMIN\/NAV2023\/NAV23195.txt"},"195\/24":{"dl_date":1726869248,"dl_url":"https:\/\/www.mynavyhr.navy.mil\/Portals\/55\/Messages\/NAVADMIN\/NAV2024\/NAV24195.txt"},"196\/23":{"dl_date":1692313478,"dl_url":"https:\/\/www.mynavyhr.navy.mil\/Portals\/55\/Messages\/NAVADMIN\/NAV2023\/NAV23196.txt"},"196\/24":{"dl_date":1726869248,"dl_url":"https:\/\/www.mynavyhr.navy.mil\/Portals\/55\/Messages\/NAVADMIN\/NAV2024\/NAV24196.txt"},"197\/23":{"dl_date":1692313478,"dl_url":"https:\/\/www.mynavyhr.navy.mil\/Portals\/55\/Messages\/NAVADMIN\/NAV2023\/NAV23197.txt"},"197\/24":{"dl_date":1727389077,"dl_url":"https:\/\/www.mynavyhr.navy.mil\/Portals\/55\/Messages\/NAVADMIN\/NAV2024\/NAV24197.txt"},"198\/23":{"dl_date":1692313477,"dl_url":"https:\/\/www.mynavyhr.navy.mil\/Portals\/55\/Messages\/NAVADMIN\/NAV2023\/NAV23198.txt"},"198\/24":{"dl_date":1727389077,"dl_url":"https:\/\/www.mynavyhr.navy.mil\/Portals\/55\/Messages\/NAVADMIN\/NAV2024\/NAV24198.txt"},"199\/23":{"dl_date":1692408282,"dl_url":"https:\/\/www.mynavyhr.navy.mil\/Portals\/55\/Messages\/NAVADMIN\/NAV2023\/NAV23199.txt"},"199\/24":{"dl_date":1727303745,"dl_url":"https:\/\/www.mynavyhr.navy.mil\/Portals\/55\/Messages\/NAVADMIN\/NAV2024\/NAV24199.txt"},"200\/23":{"dl_date":1692408282,"dl_url":"https:\/\/www.mynavyhr.navy.mil\/Portals\/55\/Messages\/NAVADMIN\/NAV2023\/NAV23200.txt"},"200\/24":{"dl_date":1727303744,"dl_url":"https:\/\/www.mynavyhr.navy.mil\/Portals\/55\/Messages\/NAVADMIN\/NAV2024\/NAV24200.txt"},"201\/23":{"dl_date":1692658952,"dl_url":"https:\/\/www.mynavyhr.navy.mil\/Portals\/55\/Messages\/NAVADMIN\/NAV2023\/NAV23201.txt"},"201\/24":{"dl_date":1727303745,"dl_url":"https:\/\/www.mynavyhr.navy.mil\/Portals\/55\/Messages\/NAVADMIN\/NAV2024\/NAV24201.txt"},"202\/23":{"dl_date":1692658952,"dl_url":"https:\/\/www.mynavyhr.navy.mil\/Portals\/55\/Messages\/NAVADMIN\/NAV2023\/NAV23202.txt"},"202\/24":{"dl_date":1727467388,"dl_url":"https:\/\/www.mynavyhr.navy.mil\/Portals\/55\/Messages\/NAVADMIN\/NAV2024\/NAV24202.txt"},"203\/23":{"dl_date":1692752415,"dl_url":"https:\/\/www.mynavyhr.navy.mil\/Portals\/55\/Messages\/NAVADMIN\/NAV2023\/NAV23203.txt"},"203\/24":{"dl_date":1727734589,"dl_url":"https:\/\/www.mynavyhr.navy.mil\/Portals\/55\/Messages\/NAVADMIN\/NAV2024\/NAV24203.txt"},"204\/23":{"dl_date":1692916789,"dl_url":"https:\/\/www.mynavyhr.navy.mil\/Portals\/55\/Messages\/NAVADMIN\/NAV2023\/NAV23204.txt"},"204\/24":{"dl_date":1727734589,"dl_url":"https:\/\/www.mynavyhr.navy.mil\/Portals\/55\/Messages\/NAVADMIN\/NAV2024\/NAV24204.txt"},"205\/23":{"dl_date":1692916789,"dl_url":"https:\/\/www.mynavyhr.navy.mil\/Portals\/55\/Messages\/NAVADMIN\/NAV2023\/NAV23205.txt"},"205\/24":{"dl_date":1727819565,"dl_url":"https:\/\/www.mynavyhr.navy.mil\/Portals\/55\/Messages\/NAVADMIN\/NAV2024\/NAV24205.txt"},"206\/23":{"dl_date":1695249146,"dl_url":"https:\/\/www.mynavyhr.navy.mil\/Portals\/55\/Messages\/NAVADMIN\/NAV2023\/NAV23206.txt"},"206\/24":{"dl_date":1729206077,"dl_url":"https:\/\/www.mynavyhr.navy.mil\/Portals\/55\/Messages\/NAVADMIN\/NAV2024\/NAV24206.txt"},"207\/23":{"dl_date":1695249146,"dl_url":"https:\/\/www.mynavyhr.navy.mil\/Portals\/55\/Messages\/NAVADMIN\/NAV2023\/NAV23207.txt"},"207\/24":{"dl_date":1727819565,"dl_url":"https:\/\/www.mynavyhr.navy.mil\/Portals\/55\/Messages\/NAVADMIN\/NAV2024\/NAV24207.txt"},"208\/23":{"dl_date":1695249146,"dl_url":"https:\/\/www.mynavyhr.navy.mil\/Portals\/55\/Messages\/NAVADMIN\/NAV2023\/NAV23208.txt"},"208\/24":{"dl_date":1728347440,"dl_url":"https:\/\/www.mynavyhr.navy.mil\/Portals\/55\/Messages\/NAVADMIN\/NAV2024\/NAV24208.txt"},"209\/23":{"dl_date":1695249146,"dl_url":"https:\/\/www.mynavyhr.navy.mil\/Portals\/55\/Messages\/NAVADMIN\/NAV2023\/NAV23209.txt"},"209\/24":{"dl_date":1728347439,"dl_url":"https:\/\/www.mynavyhr.navy.mil\/Portals\/55\/Messages\/NAVADMIN\/NAV2024\/NAV24209.txt"},"210\/23":{"dl_date":1695249146,"dl_url":"https:\/\/www.mynavyhr.navy.mil\/Portals\/55\/Messages\/NAVADMIN\/NAV2023\/NAV23210.txt"},"210\/24":{"dl_date":1728516379,"dl_url":"https:\/\/www.mynavyhr.navy.mil\/Portals\/55\/Messages\/NAVADMIN\/NAV2024\/NAV24210.txt"},"211\/23":{"dl_date":1695249146,"dl_url":"https:\/\/www.mynavyhr.navy.mil\/Portals\/55\/Messages\/NAVADMIN\/NAV2023\/NAV23211.txt"},"211\/24":{"dl_date":1728516379,"dl_url":"https:\/\/www.mynavyhr.navy.mil\/Portals\/55\/Messages\/NAVADMIN\/NAV2024\/NAV24211.txt"},"212\/23":{"dl_date":1695249146,"dl_url":"https:\/\/www.mynavyhr.navy.mil\/Portals\/55\/Messages\/NAVADMIN\/NAV2023\/NAV23212.txt"},"212\/24":{"dl_date":1728516379,"dl_url":"https:\/\/www.mynavyhr.navy.mil\/Portals\/55\/Messages\/NAVADMIN\/NAV2024\/NAV24212.txt"},"213\/23":{"dl_date":1695249146,"dl_url":"https:\/\/www.mynavyhr.navy.mil\/Portals\/55\/Messages\/NAVADMIN\/NAV2023\/NAV23213.txt"},"213\/24":{"dl_date":1728600226,"dl_url":"https:\/\/www.mynavyhr.navy.mil\/Portals\/55\/Messages\/NAVADMIN\/NAV2024\/NAV24213.txt"},"214\/23":{"dl_date":1695249146,"dl_url":"https:\/\/www.mynavyhr.navy.mil\/Portals\/55\/Messages\/NAVADMIN\/NAV2023\/NAV23214.txt"},"214\/24":{"dl_date":1729043310,"dl_url":"https:\/\/www.mynavyhr.navy.mil\/Portals\/55\/Messages\/NAVADMIN\/NAV2024\/NAV24214.txt"},"215\/23":{"dl_date":1695249145,"dl_url":"https:\/\/www.mynavyhr.navy.mil\/Portals\/55\/Messages\/NAVADMIN\/NAV2023\/NAV23215.txt"},"215\/24":{"dl_date":1729128519,"dl_url":"https:\/\/www.mynavyhr.navy.mil\/Portals\/55\/Messages\/NAVADMIN\/NAV2024\/NAV24215.txt"},"216\/23":{"dl_date":1695249145,"dl_url":"https:\/\/www.mynavyhr.navy.mil\/Portals\/55\/Messages\/NAVADMIN\/NAV2023\/NAV23216.txt"},"216\/24":{"dl_date":1729128519,"dl_url":"https:\/\/www.mynavyhr.navy.mil\/Portals\/55\/Messages\/NAVADMIN\/NAV2024\/NAV24216.txt"},"217\/23":{"dl_date":1694837217,"dl_url":"https:\/\/www.mynavyhr.navy.mil\/Portals\/55\/Messages\/NAVADMIN\/NAV2023\/NAV23217.txt"},"217\/24":{"dl_date":1729555882,"dl_url":"https:\/\/www.mynavyhr.navy.mil\/Portals\/55\/Messages\/NAVADMIN\/NAV2024\/NAV24217.txt"},"218\/23":{"dl_date":1694837217,"dl_url":"https:\/\/www.mynavyhr.navy.mil\/Portals\/55\/Messages\/NAVADMIN\/NAV2023\/NAV23218.txt"},"218\/24":{"dl_date":1729723037,"dl_url":"https:\/\/www.mynavyhr.navy.mil\/Portals\/55\/Messages\/NAVADMIN\/NAV2024\/NAV24218.txt"},"219\/23":{"dl_date":1694837217,"dl_url":"https:\/\/www.mynavyhr.navy.mil\/Portals\/55\/Messages\/NAVADMIN\/NAV2023\/NAV23219.txt"},"219\/24":{"dl_date":1729723037,"dl_url":"https:\/\/www.mynavyhr.navy.mil\/Portals\/55\/Messages\/NAVADMIN\/NAV2024\/NAV24219.txt"},"220\/23":{"dl_date":1695080682,"dl_url":"https:\/\/www.mynavyhr.navy.mil\/Portals\/55\/Messages\/NAVADMIN\/NAV2023\/NAV23220.txt"},"220\/24":{"dl_date":1729723037,"dl_url":"https:\/\/www.mynavyhr.navy.mil\/Portals\/55\/Messages\/NAVADMIN\/NAV2024\/NAV24220.txt"},"221\/22":{"dl_date":1664560910,"dl_url":"https:\/\/www.mynavyhr.navy.mil\/Portals\/55\/Messages\/NAVADMIN\/NAV2022\/NAV22221.txt"},"221\/23":{"dl_date":1695080682,"dl_url":"https:\/\/www.mynavyhr.navy.mil\/Portals\/55\/Messages\/NAVADMIN\/NAV2023\/NAV23221.txt"},"221\/24":{"dl_date":1730242115,"dl_url":"https:\/\/www.mynavyhr.navy.mil\/Portals\/55\/Messages\/NAVADMIN\/NAV2024\/NAV24221.txt"},"222\/15":{"dl_date":1735748920,"dl_url":"https:\/\/www.mynavyhr.navy.mil\/Portals\/55\/Messages\/NAVADMIN\/NAV2015\/NAV15222.txt"},"222\/22":{"dl_date":1664923063,"dl_url":"https:\/\/www.mynavyhr.navy.mil\/Portals\/55\/Messages\/NAVADMIN\/NAV2022\/NAV22222.txt"},"222\/23":{"dl_date":1695171183,"dl_url":"https:\/\/www.mynavyhr.navy.mil\/Portals\/55\/Messages\/NAVADMIN\/NAV2023\/NAV23222.txt"},"222\/24":{"dl_date":1732998082,"dl_url":"https:\/\/www.mynavyhr.navy.mil\/Portals\/55\/Messages\/NAVADMIN\/NAV2024\/NAV24222.txt"},"223\/22":{"dl_date":1664923063,"dl_url":"https:\/\/www.mynavyhr.navy.mil\/Portals\/55\/Messages\/NAVADMIN\/NAV2022\/NAV22223.txt"},"223\/23":{"dl_date":1695335172,"dl_url":"https:\/\/www.mynavyhr.navy.mil\/Portals\/55\/Messages\/NAVADMIN\/NAV2023\/NAV23223.txt"},"223\/24":{"dl_date":1730326164,"dl_url":"https:\/\/www.mynavyhr.navy.mil\/Portals\/55\/Messages\/NAVADMIN\/NAV2024\/NAV24223.txt"},"224\/22":{"dl_date":1664923063,"dl_url":"https:\/\/www.mynavyhr.navy.mil\/Portals\/55\/Messages\/NAVADMIN\/NAV2022\/NAV22224.txt"},"224\/23":{"dl_date":1695335172,"dl_url":"https:\/\/www.mynavyhr.navy.mil\/Portals\/55\/Messages\/NAVADMIN\/NAV2023\/NAV23224.txt"},"224\/24":{"dl_date":1730413458,"dl_url":"https:\/\/www.mynavyhr.navy.mil\/Portals\/55\/Messages\/NAVADMIN\/NAV2024\/NAV24224.txt"},"225\/22":{"dl_date":1664923062,"dl_url":"https:\/\/www.mynavyhr.navy.mil\/Portals\/55\/Messages\/NAVADMIN\/NAV2022\/NAV22225.txt"},"225\/23":{"dl_date":1695335172,"dl_url":"https:\/\/www.mynavyhr.navy.mil\/Portals\/55\/Messages\/NAVADMIN\/NAV2023\/NAV23225.txt"},"225\/24":{"dl_date":1730768330,"dl_url":"https:\/\/www.mynavyhr.navy.mil\/Portals\/55\/Messages\/NAVADMIN\/NAV2024\/NAV24225.txt"},"226\/22":{"dl_date":1665014155,"dl_url":"https:\/\/www.mynavyhr.navy.mil\/Portals\/55\/Messages\/NAVADMIN\/NAV2022\/NAV22226.txt"},"226\/23":{"dl_date":1695335172,"dl_url":"https:\/\/www.mynavyhr.navy.mil\/Portals\/55\/Messages\/NAVADMIN\/NAV2023\/NAV23226.txt"},"226\/24":{"dl_date":1730843864,"dl_url":"https:\/\/www.mynavyhr.navy.mil\/Portals\/55\/Messages\/NAVADMIN\/NAV2024\/NAV24226.txt"},"227\/22":{"dl_date":1665100568,"dl_url":"https:\/\/www.mynavyhr.navy.mil\/Portals\/55\/Messages\/NAVADMIN\/NAV2022\/NAV22227.txt"},"227\/23":{"dl_date":1697157300,"dl_url":"https:\/\/www.mynavyhr.navy.mil\/Portals\/55\/Messages\/NAVADMIN\/NAV2023\/NAV23227.txt"},"227\/24":{"dl_date":1730843864,"dl_url":"https:\/\/www.mynavyhr.navy.mil\/Portals\/55\/Messages\/NAVADMIN\/NAV2024\/NAV24227.txt"},"228\/22":{"dl_date":1665252245,"dl_url":"https:\/\/www.mynavyhr.navy.mil\/Portals\/55\/Messages\/NAVADMIN\/NAV2022\/NAV22228.txt"},"228\/23":{"dl_date":1695673989,"dl_url":"https:\/\/www.mynavyhr.navy.mil\/Portals\/55\/Messages\/NAVADMIN\/NAV2023\/NAV23228.txt"},"228\/24":{"dl_date":1730931104,"dl_url":"https:\/\/www.mynavyhr.navy.mil\/Portals\/55\/Messages\/NAVADMIN\/NAV2024\/NAV24228.txt"},"229\/22":{"dl_date":1665252244,"dl_url":"https:\/\/www.mynavyhr.navy.mil\/Portals\/55\/Messages\/NAVADMIN\/NAV2022\/NAV22229.txt"},"229\/23":{"dl_date":1695763476,"dl_url":"https:\/\/www.mynavyhr.navy.mil\/Portals\/55\/Messages\/NAVADMIN\/NAV2023\/NAV23229.txt"},"229\/24":{"dl_date":1731073134,"dl_url":"https:\/\/www.mynavyhr.navy.mil\/Portals\/55\/Messages\/NAVADMIN\/NAV2024\/NAV24229.txt"},"230\/22":{"dl_date":1665252244,"dl_url":"https:\/\/www.mynavyhr.navy.mil\/Portals\/55\/Messages\/NAVADMIN\/NAV2022\/NAV22230.txt"},"230\/23":{"dl_date":1695763476,"dl_url":"https:\/\/www.mynavyhr.navy.mil\/Portals\/55\/Messages\/NAVADMIN\/NAV2023\/NAV23230.txt"},"230\/24":{"dl_date":1731161207,"dl_url":"https:\/\/www.mynavyhr.navy.mil\/Portals\/55\/Messages\/NAVADMIN\/NAV2024\/NAV24230.txt"},"231\/22":{"dl_date":1665613119,"dl_url":"https:\/\/www.mynavyhr.navy.mil\/Portals\/55\/Messages\/NAVADMIN\/NAV2022\/NAV22231.txt"},"231\/23":{"dl_date":1695763476,"dl_url":"https:\/\/www.mynavyhr.navy.mil\/Portals\/55\/Messages\/NAVADMIN\/NAV2023\/NAV23231.txt"},"231\/24":{"dl_date":1731444366,"dl_url":"https:\/\/www.mynavyhr.navy.mil\/Portals\/55\/Messages\/NAVADMIN\/NAV2024\/NAV24231.txt"},"232\/22":{"dl_date":1665613119,"dl_url":"https:\/\/www.mynavyhr.navy.mil\/Portals\/55\/Messages\/NAVADMIN\/NAV2022\/NAV22232.txt"},"232\/23":{"dl_date":1695763476,"dl_url":"https:\/\/www.mynavyhr.navy.mil\/Portals\/55\/Messages\/NAVADMIN\/NAV2023\/NAV23232.txt"},"232\/24":{"dl_date":1731444366,"dl_url":"https:\/\/www.mynavyhr.navy.mil\/Portals\/55\/Messages\/NAVADMIN\/NAV2024\/NAV24232.txt"},"233\/22":{"dl_date":1665613118,"dl_url":"https:\/\/www.mynavyhr.navy.mil\/Portals\/55\/Messages\/NAVADMIN\/NAV2022\/NAV22233.txt"},"233\/23":{"dl_date":1695763476,"dl_url":"https:\/\/www.mynavyhr.navy.mil\/Portals\/55\/Messages\/NAVADMIN\/NAV2023\/NAV23233.txt"},"233\/24":{"dl_date":1731698774,"dl_url":"https:\/\/www.mynavyhr.navy.mil\/Portals\/55\/Messages\/NAVADMIN\/NAV2024\/NAV24233.txt"},"234\/04":{"dl_date":1735748920,"dl_url":"https:\/\/www.mynavyhr.navy.mil\/Portals\/55\/Messages\/NAVADMIN\/NAV2004\/nav04234.txt"},"234\/22":{"dl_date":1666747754,"dl_url":"https:\/\/www.mynavyhr.navy.mil\/Portals\/55\/Messages\/NAVADMIN\/NAV2022\/NAV22234.txt"},"234\/23":{"dl_date":1696077841,"dl_url":"https:\/\/www.mynavyhr.navy.mil\/Portals\/55\/Messages\/NAVADMIN\/NAV2023\/NAV23234.txt"},"234\/24":{"dl_date":1731690967,"dl_url":"https:\/\/www.mynavyhr.navy.mil\/Portals\/55\/Messages\/NAVADMIN\/NAV2024\/NAV24234.txt"},"235\/22":{"dl_date":1666302034,"dl_url":"https:\/\/www.mynavyhr.navy.mil\/Portals\/55\/Messages\/NAVADMIN\/NAV2022\/NAV22235.txt"},"235\/23":{"dl_date":1696287450,"dl_url":"https:\/\/www.mynavyhr.navy.mil\/Portals\/55\/Messages\/NAVADMIN\/NAV2023\/NAV23235.txt"},"235\/24":{"dl_date":1731698774,"dl_url":"https:\/\/www.mynavyhr.navy.mil\/Portals\/55\/Messages\/NAVADMIN\/NAV2024\/NAV24235.txt"},"236\/22":{"dl_date":1666302034,"dl_url":"https:\/\/www.mynavyhr.navy.mil\/Portals\/55\/Messages\/NAVADMIN\/NAV2022\/NAV22236.txt"},"236\/23":{"dl_date":1696539480,"dl_url":"https:\/\/www.mynavyhr.navy.mil\/Portals\/55\/Messages\/NAVADMIN\/NAV2023\/NAV23236.txt"},"236\/24":{"dl_date":1732025214,"dl_url":"https:\/\/www.mynavyhr.navy.mil\/Portals\/55\/Messages\/NAVADMIN\/NAV2024\/NAV24236.txt"},"237\/22":{"dl_date":1666302034,"dl_url":"https:\/\/www.mynavyhr.navy.mil\/Portals\/55\/Messages\/NAVADMIN\/NAV2022\/NAV22237.txt"},"237\/23":{"dl_date":1696371435,"dl_url":"https:\/\/www.mynavyhr.navy.mil\/Portals\/55\/Messages\/NAVADMIN\/NAV2023\/NAV23237.txt"},"237\/24":{"dl_date":1732111303,"dl_url":"https:\/\/www.mynavyhr.navy.mil\/Portals\/55\/Messages\/NAVADMIN\/NAV2024\/NAV24237.txt"},"238\/22":{"dl_date":1666302033,"dl_url":"https:\/\/www.mynavyhr.navy.mil\/Portals\/55\/Messages\/NAVADMIN\/NAV2022\/NAV22238.txt"},"238\/23":{"dl_date":1696371435,"dl_url":"https:\/\/www.mynavyhr.navy.mil\/Portals\/55\/Messages\/NAVADMIN\/NAV2023\/NAV23238.txt"},"238\/24":{"dl_date":1732111303,"dl_url":"https:\/\/www.mynavyhr.navy.mil\/Portals\/55\/Messages\/NAVADMIN\/NAV2024\/NAV24238.txt"},"239\/22":{"dl_date":1666747753,"dl_url":"https:\/\/www.mynavyhr.navy.mil\/Portals\/55\/Messages\/NAVADMIN\/NAV2022\/NAV22239.txt"},"239\/23":{"dl_date":1696460787,"dl_url":"https:\/\/www.mynavyhr.navy.mil\/Portals\/55\/Messages\/NAVADMIN\/NAV2023\/NAV23239.txt"},"239\/24":{"dl_date":1732111303,"dl_url":"https:\/\/www.mynavyhr.navy.mil\/Portals\/55\/Messages\/NAVADMIN\/NAV2024\/NAV24239.txt"},"240\/22":{"dl_date":1666823363,"dl_url":"https:\/\/www.mynavyhr.navy.mil\/Portals\/55\/Messages\/NAVADMIN\/NAV2022\/NAV22240.txt"},"240\/23":{"dl_date":1696684404,"dl_url":"https:\/\/www.mynavyhr.navy.mil\/Portals\/55\/Messages\/NAVADMIN\/NAV2023\/NAV23240.txt"},"241\/22":{"dl_date":1666823362,"dl_url":"https:\/\/www.mynavyhr.navy.mil\/Portals\/55\/Messages\/NAVADMIN\/NAV2022\/NAV22241.txt"},"241\/23":{"dl_date":1696684404,"dl_url":"https:\/\/www.mynavyhr.navy.mil\/Portals\/55\/Messages\/NAVADMIN\/NAV2023\/NAV23241.txt"},"241\/24":{"dl_date":1732226666,"dl_url":"https:\/\/www.mynavyhr.navy.mil\/Portals\/55\/Messages\/NAVADMIN\/NAV2024\/NAV24241.txt"},"242\/22":{"dl_date":1666823362,"dl_url":"https:\/\/www.mynavyhr.navy.mil\/Portals\/55\/Messages\/NAVADMIN\/NAV2022\/NAV22242.txt"},"242\/23":{"dl_date":1697157299,"dl_url":"https:\/\/www.mynavyhr.navy.mil\/Portals\/55\/Messages\/NAVADMIN\/NAV2023\/NAV23242.txt"},"242\/24":{"dl_date":1732805023,"dl_url":"https:\/\/www.mynavyhr.navy.mil\/Portals\/55\/Messages\/NAVADMIN\/NAV2024\/NAV24242.txt"},"243\/22":{"dl_date":1666909511,"dl_url":"https:\/\/www.mynavyhr.navy.mil\/Portals\/55\/Messages\/NAVADMIN\/NAV2022\/NAV22243.txt"},"243\/23":{"dl_date":1697157299,"dl_url":"https:\/\/www.mynavyhr.navy.mil\/Portals\/55\/Messages\/NAVADMIN\/NAV2023\/NAV23243.txt"},"243\/24":{"dl_date":1732648941,"dl_url":"https:\/\/www.mynavyhr.navy.mil\/Portals\/55\/Messages\/NAVADMIN\/NAV2024\/NAV24243.txt"},"244\/14":{"dl_date":1735748920,"dl_url":"https:\/\/www.mynavyhr.navy.mil\/Portals\/55\/Messages\/NAVADMIN\/NAV2014\/NAV14244.txt"},"244\/22":{"dl_date":1666909511,"dl_url":"https:\/\/www.mynavyhr.navy.mil\/Portals\/55\/Messages\/NAVADMIN\/NAV2022\/NAV22244.txt"},"244\/23":{"dl_date":1697157299,"dl_url":"https:\/\/www.mynavyhr.navy.mil\/Portals\/55\/Messages\/NAVADMIN\/NAV2023\/NAV23244.txt"},"244\/24":{"dl_date":1732805023,"dl_url":"https:\/\/www.mynavyhr.navy.mil\/Portals\/55\/Messages\/NAVADMIN\/NAV2024\/NAV24244.txt"},"245\/22":{"dl_date":1666996073,"dl_url":"https:\/\/www.mynavyhr.navy.mil\/Portals\/55\/Messages\/NAVADMIN\/NAV2022\/NAV22245.txt"},"245\/23":{"dl_date":1697755740,"dl_url":"https:\/\/www.mynavyhr.navy.mil\/Portals\/55\/Messages\/NAVADMIN\/NAV2023\/NAV23245.txt"},"245\/24":{"dl_date":1733430786,"dl_url":"https:\/\/www.mynavyhr.navy.mil\/Portals\/55\/Messages\/NAVADMIN\/NAV2024\/NAV24245.txt"},"246\/22":{"dl_date":1666996072,"dl_url":"https:\/\/www.mynavyhr.navy.mil\/Portals\/55\/Messages\/NAVADMIN\/NAV2022\/NAV22246.txt"},"246\/23":{"dl_date":1697157299,"dl_url":"https:\/\/www.mynavyhr.navy.mil\/Portals\/55\/Messages\/NAVADMIN\/NAV2023\/NAV23246.txt"},"246\/24":{"dl_date":1733785401,"dl_url":"https:\/\/www.mynavyhr.navy.mil\/Portals\/55\/Messages\/NAVADMIN\/NAV2024\/NAV24246.txt"},"247\/22":{"dl_date":1667255991,"dl_url":"https:\/\/www.mynavyhr.navy.mil\/Portals\/55\/Messages\/NAVADMIN\/NAV2022\/NAV22247.txt"},"247\/23":{"dl_date":1697157299,"dl_url":"https:\/\/www.mynavyhr.navy.mil\/Portals\/55\/Messages\/NAVADMIN\/NAV2023\/NAV23247.txt"},"247\/24":{"dl_date":1733869259,"dl_url":"https:\/\/www.mynavyhr.navy.mil\/Portals\/55\/Messages\/NAVADMIN\/NAV2024\/NAV24247.txt"},"248\/22":{"dl_date":1667255991,"dl_url":"https:\/\/www.mynavyhr.navy.mil\/Portals\/55\/Messages\/NAVADMIN\/NAV2022\/NAV22248.txt"},"248\/23":{"dl_date":1697229939,"dl_url":"https:\/\/www.mynavyhr.navy.mil\/Portals\/55\/Messages\/NAVADMIN\/NAV2023\/NAV23248.txt"},"248\/24":{"dl_date":1733948833,"dl_url":"https:\/\/www.mynavyhr.navy.mil\/Portals\/55\/Messages\/NAVADMIN\/NAV2024\/NAV24248.txt"},"249\/22":{"dl_date":1667608671,"dl_url":"https:\/\/www.mynavyhr.navy.mil\/Portals\/55\/Messages\/NAVADMIN\/NAV2022\/NAV22249.txt"},"249\/23":{"dl_date":1697504794,"dl_url":"https:\/\/www.mynavyhr.navy.mil\/Portals\/55\/Messages\/NAVADMIN\/NAV2023\/NAV23249.txt"},"249\/24":{"dl_date":1734713331,"dl_url":"https:\/\/www.mynavyhr.navy.mil\/Portals\/55\/Messages\/NAVADMIN\/NAV2024\/NAV24249.txt"},"250\/22":{"dl_date":1667608671,"dl_url":"https:\/\/www.mynavyhr.navy.mil\/Portals\/55\/Messages\/NAVADMIN\/NAV2022\/NAV22250.txt"},"250\/23":{"dl_date":1697587156,"dl_url":"https:\/\/www.mynavyhr.navy.mil\/Portals\/55\/Messages\/NAVADMIN\/NAV2023\/NAV23250.txt"},"250\/24":{"dl_date":1734403717,"dl_url":"https:\/\/www.mynavyhr.navy.mil\/Portals\/55\/Messages\/NAVADMIN\/NAV2024\/NAV24250.txt"},"251\/22":{"dl_date":1667608671,"dl_url":"https:\/\/www.mynavyhr.navy.mil\/Portals\/55\/Messages\/NAVADMIN\/NAV2022\/NAV22251.txt"},"251\/23":{"dl_date":1698099813,"dl_url":"https:\/\/www.mynavyhr.navy.mil\/Portals\/55\/Messages\/NAVADMIN\/NAV2023\/NAV23251.txt"},"251\/24":{"dl_date":1734403717,"dl_url":"https:\/\/www.mynavyhr.navy.mil\/Portals\/55\/Messages\/NAVADMIN\/NAV2024\/NAV24251.txt"},"252\/22":{"dl_date":1668038154,"dl_url":"https:\/\/www.mynavyhr.navy.mil\/Portals\/55\/Messages\/NAVADMIN\/NAV2022\/NAV22252.txt"},"252\/23":{"dl_date":1698099813,"dl_url":"https:\/\/www.mynavyhr.navy.mil\/Portals\/55\/Messages\/NAVADMIN\/NAV2023\/NAV23252.txt"},"252\/24":{"dl_date":1734485956,"dl_url":"https:\/\/www.mynavyhr.navy.mil\/Portals\/55\/Messages\/NAVADMIN\/NAV2024\/NAV24252.txt"},"253\/22":{"dl_date":1668038154,"dl_url":"https:\/\/www.mynavyhr.navy.mil\/Portals\/55\/Messages\/NAVADMIN\/NAV2022\/NAV22253.txt"},"253\/23":{"dl_date":1698275854,"dl_url":"https:\/\/www.mynavyhr.navy.mil\/Portals\/55\/Messages\/NAVADMIN\/NAV2023\/NAV23253.txt"},"253\/24":{"dl_date":1734559961,"dl_url":"https:\/\/www.mynavyhr.navy.mil\/Portals\/55\/Messages\/NAVADMIN\/NAV2024\/NAV24253.txt"},"254\/22":{"dl_date":1668125731,"dl_url":"https:\/\/www.mynavyhr.navy.mil\/Portals\/55\/Messages\/NAVADMIN\/NAV2022\/NAV22254.txt"},"254\/23":{"dl_date":1698444559,"dl_url":"https:\/\/www.mynavyhr.navy.mil\/Portals\/55\/Messages\/NAVADMIN\/NAV2023\/NAV23254.txt"},"254\/24":{"dl_date":1734559961,"dl_url":"https:\/\/www.mynavyhr.navy.mil\/Portals\/55\/Messages\/NAVADMIN\/NAV2024\/NAV24254.txt"},"255\/22":{"dl_date":1668565831,"dl_url":"https:\/\/www.mynavyhr.navy.mil\/Portals\/55\/Messages\/NAVADMIN\/NAV2022\/NAV22255.txt"},"255\/23":{"dl_date":1698704943,"dl_url":"https:\/\/www.mynavyhr.navy.mil\/Portals\/55\/Messages\/NAVADMIN\/NAV2023\/NAV23255.txt"},"255\/24":{"dl_date":1734713331,"dl_url":"https:\/\/www.mynavyhr.navy.mil\/Portals\/55\/Messages\/NAVADMIN\/NAV2024\/NAV24255.txt"},"256\/22":{"dl_date":1668811998,"dl_url":"https:\/\/www.mynavyhr.navy.mil\/Portals\/55\/Messages\/NAVADMIN\/NAV2022\/NAV22256.txt"},"256\/23":{"dl_date":1698704947,"dl_url":"https:\/\/www.mynavyhr.navy.mil\/Portals\/55\/Messages\/NAVADMIN\/NAV2023\/NAV23256.txt"},"256\/24":{"dl_date":1734984374,"dl_url":"https:\/\/www.mynavyhr.navy.mil\/Portals\/55\/Messages\/NAVADMIN\/NAV2024\/NAV24256.txt"},"257\/22":{"dl_date":1668811997,"dl_url":"https:\/\/www.mynavyhr.navy.mil\/Portals\/55\/Messages\/NAVADMIN\/NAV2022\/NAV22257.txt"},"257\/23":{"dl_date":1698704943,"dl_url":"https:\/\/www.mynavyhr.navy.mil\/Portals\/55\/Messages\/NAVADMIN\/NAV2023\/NAV23257.txt"},"257\/24":{"dl_date":1734984374,"dl_url":"https:\/\/www.mynavyhr.navy.mil\/Portals\/55\/Messages\/NAVADMIN\/NAV2024\/NAV24257.txt"},"258\/22":{"dl_date":1668811997,"dl_url":"https:\/\/www.mynavyhr.navy.mil\/Portals\/55\/Messages\/NAVADMIN\/NAV2022\/NAV22258.txt"},"258\/23":{"dl_date":1698704943,"dl_url":"https:\/\/www.mynavyhr.navy.mil\/Portals\/55\/Messages\/NAVADMIN\/NAV2023\/NAV23258.txt"},"258\/24":{"dl_date":1734984374,"dl_url":"https:\/\/www.mynavyhr.navy.mil\/Portals\/55\/Messages\/NAVADMIN\/NAV2024\/NAV24258.txt"},"259\/22":{"dl_date":1668811997,"dl_url":"https:\/\/www.mynavyhr.navy.mil\/Portals\/55\/Messages\/NAVADMIN\/NAV2022\/NAV22259.txt"},"259\/23":{"dl_date":1699049125,"dl_url":"https:\/\/www.mynavyhr.navy.mil\/Portals\/55\/Messages\/NAVADMIN\/NAV2023\/NAV23259.txt"},"259\/24":{"dl_date":1734984374,"dl_url":"https:\/\/www.mynavyhr.navy.mil\/Portals\/55\/Messages\/NAVADMIN\/NAV2024\/NAV24259.txt"},"260\/22":{"dl_date":1668811997,"dl_url":"https:\/\/www.mynavyhr.navy.mil\/Portals\/55\/Messages\/NAVADMIN\/NAV2022\/NAV22260.txt"},"260\/23":{"dl_date":1698962741,"dl_url":"https:\/\/www.mynavyhr.navy.mil\/Portals\/55\/Messages\/NAVADMIN\/NAV2023\/NAV23260.txt"},"260\/24":{"dl_date":1735078548,"dl_url":"https:\/\/www.mynavyhr.navy.mil\/Portals\/55\/Messages\/NAVADMIN\/NAV2024\/NAV24260.txt"},"261\/22":{"dl_date":1669163998,"dl_url":"https:\/\/www.mynavyhr.navy.mil\/Portals\/55\/Messages\/NAVADMIN\/NAV2022\/NAV22261.txt"},"261\/23":{"dl_date":1699049124,"dl_url":"https:\/\/www.mynavyhr.navy.mil\/Portals\/55\/Messages\/NAVADMIN\/NAV2023\/NAV23261.txt"},"261\/24":{"dl_date":1735597632,"dl_url":"https:\/\/www.mynavyhr.navy.mil\/Portals\/55\/Messages\/NAVADMIN\/NAV2024\/NAV24261.txt"},"262\/22":{"dl_date":1669234145,"dl_url":"https:\/\/www.mynavyhr.navy.mil\/Portals\/55\/Messages\/NAVADMIN\/NAV2022\/NAV22262.txt"},"262\/23":{"dl_date":1699049129,"dl_url":"https:\/\/www.mynavyhr.navy.mil\/Portals\/55\/Messages\/NAVADMIN\/NAV2023\/NAV23262.txt"},"263\/22":{"dl_date":1669234145,"dl_url":"https:\/\/www.mynavyhr.navy.mil\/Portals\/55\/Messages\/NAVADMIN\/NAV2022\/NAV22263.txt"},"263\/23":{"dl_date":1699049125,"dl_url":"https:\/\/www.mynavyhr.navy.mil\/Portals\/55\/Messages\/NAVADMIN\/NAV2023\/NAV23263.txt"},"264\/22":{"dl_date":1669234145,"dl_url":"https:\/\/www.mynavyhr.navy.mil\/Portals\/55\/Messages\/NAVADMIN\/NAV2022\/NAV22264.txt"},"264\/23":{"dl_date":1699049125,"dl_url":"https:\/\/www.mynavyhr.navy.mil\/Portals\/55\/Messages\/NAVADMIN\/NAV2023\/NAV23264.txt"},"265\/22":{"dl_date":1669678337,"dl_url":"https:\/\/www.mynavyhr.navy.mil\/Portals\/55\/Messages\/NAVADMIN\/NAV2022\/NAV22265.txt"},"265\/23":{"dl_date":1699049130,"dl_url":"https:\/\/www.mynavyhr.navy.mil\/Portals\/55\/Messages\/NAVADMIN\/NAV2023\/NAV23265.txt"},"266\/22":{"dl_date":1669678337,"dl_url":"https:\/\/www.mynavyhr.navy.mil\/Portals\/55\/Messages\/NAVADMIN\/NAV2022\/NAV22266.txt"},"266\/23":{"dl_date":1699049130,"dl_url":"https:\/\/www.mynavyhr.navy.mil\/Portals\/55\/Messages\/NAVADMIN\/NAV2023\/NAV23266.txt"},"267\/22":{"dl_date":1669678337,"dl_url":"https:\/\/www.mynavyhr.navy.mil\/Portals\/55\/Messages\/NAVADMIN\/NAV2022\/NAV22267.txt"},"267\/23":{"dl_date":1699317071,"dl_url":"https:\/\/www.mynavyhr.navy.mil\/Portals\/55\/Messages\/NAVADMIN\/NAV2023\/NAV23267.txt"},"268\/22":{"dl_date":1669854224,"dl_url":"https:\/\/www.mynavyhr.navy.mil\/Portals\/55\/Messages\/NAVADMIN\/NAV2022\/NAV22268.txt"},"268\/23":{"dl_date":1699399762,"dl_url":"https:\/\/www.mynavyhr.navy.mil\/Portals\/55\/Messages\/NAVADMIN\/NAV2023\/NAV23268.txt"},"269\/22":{"dl_date":1669939067,"dl_url":"https:\/\/www.mynavyhr.navy.mil\/Portals\/55\/Messages\/NAVADMIN\/NAV2022\/NAV22269.txt"},"269\/23":{"dl_date":1699399762,"dl_url":"https:\/\/www.mynavyhr.navy.mil\/Portals\/55\/Messages\/NAVADMIN\/NAV2023\/NAV23269.txt"},"270\/22":{"dl_date":1669939067,"dl_url":"https:\/\/www.mynavyhr.navy.mil\/Portals\/55\/Messages\/NAVADMIN\/NAV2022\/NAV22270.txt"},"270\/23":{"dl_date":1699484180,"dl_url":"https:\/\/www.mynavyhr.navy.mil\/Portals\/55\/Messages\/NAVADMIN\/NAV2023\/NAV23270.txt"},"271\/22":{"dl_date":1670023114,"dl_url":"https:\/\/www.mynavyhr.navy.mil\/Portals\/55\/Messages\/NAVADMIN\/NAV2022\/NAV22271.txt"},"271\/23":{"dl_date":1699484179,"dl_url":"https:\/\/www.mynavyhr.navy.mil\/Portals\/55\/Messages\/NAVADMIN\/NAV2023\/NAV23271.txt"},"272\/22":{"dl_date":1670278032,"dl_url":"https:\/\/www.mynavyhr.navy.mil\/Portals\/55\/Messages\/NAVADMIN\/NAV2022\/NAV22272.txt"},"272\/23":{"dl_date":1699566947,"dl_url":"https:\/\/www.mynavyhr.navy.mil\/Portals\/55\/Messages\/NAVADMIN\/NAV2023\/NAV23272.txt"},"273\/22":{"dl_date":1670458061,"dl_url":"https:\/\/www.mynavyhr.navy.mil\/Portals\/55\/Messages\/NAVADMIN\/NAV2022\/NAV22273.txt"},"273\/23":{"dl_date":1699572539,"dl_url":"https:\/\/www.mynavyhr.navy.mil\/Portals\/55\/Messages\/NAVADMIN\/NAV2023\/NAV23273.txt"},"274\/22":{"dl_date":1670529281,"dl_url":"https:\/\/www.mynavyhr.navy.mil\/Portals\/55\/Messages\/NAVADMIN\/NAV2022\/NAV22274.txt"},"274\/23":{"dl_date":1700183331,"dl_url":"https:\/\/www.mynavyhr.navy.mil\/Portals\/55\/Messages\/NAVADMIN\/NAV2023\/NAV23274.txt"},"275\/22":{"dl_date":1670610233,"dl_url":"https:\/\/www.mynavyhr.navy.mil\/Portals\/55\/Messages\/NAVADMIN\/NAV2022\/NAV22275.txt"},"275\/23":{"dl_date":1700183331,"dl_url":"https:\/\/www.mynavyhr.navy.mil\/Portals\/55\/Messages\/NAVADMIN\/NAV2023\/NAV23275.txt"},"276\/22":{"dl_date":1670808975,"dl_url":"https:\/\/www.mynavyhr.navy.mil\/Portals\/55\/Messages\/NAVADMIN\/NAV2022\/NAV22276.txt"},"276\/23":{"dl_date":1700183331,"dl_url":"https:\/\/www.mynavyhr.navy.mil\/Portals\/55\/Messages\/NAVADMIN\/NAV2023\/NAV23276.txt"},"277\/22":{"dl_date":1670808975,"dl_url":"https:\/\/www.mynavyhr.navy.mil\/Portals\/55\/Messages\/NAVADMIN\/NAV2022\/NAV22277.txt"},"277\/23":{"dl_date":1700519135,"dl_url":"https:\/\/www.mynavyhr.navy.mil\/Portals\/55\/Messages\/NAVADMIN\/NAV2023\/NAV23277.txt"},"278\/22":{"dl_date":1670808974,"dl_url":"https:\/\/www.mynavyhr.navy.mil\/Portals\/55\/Messages\/NAVADMIN\/NAV2022\/NAV22278.txt"},"278\/23":{"dl_date":1700519135,"dl_url":"https:\/\/www.mynavyhr.navy.mil\/Portals\/55\/Messages\/NAVADMIN\/NAV2023\/NAV23278.txt"},"279\/22":{"dl_date":1670974602,"dl_url":"https:\/\/www.mynavyhr.navy.mil\/Portals\/55\/Messages\/NAVADMIN\/NAV2022\/NAV22279.txt"},"279\/23":{"dl_date":1700519135,"dl_url":"https:\/\/www.mynavyhr.navy.mil\/Portals\/55\/Messages\/NAVADMIN\/NAV2023\/NAV23279.txt"},"280\/22":{"dl_date":1670974602,"dl_url":"https:\/\/www.mynavyhr.navy.mil\/Portals\/55\/Messages\/NAVADMIN\/NAV2022\/NAV22280.txt"},"280\/23":{"dl_date":1700519135,"dl_url":"https:\/\/www.mynavyhr.navy.mil\/Portals\/55\/Messages\/NAVADMIN\/NAV2023\/NAV23280.txt"},"281\/22":{"dl_date":1671382442,"dl_url":"https:\/\/www.mynavyhr.navy.mil\/Portals\/55\/Messages\/NAVADMIN\/NAV2022\/NAV22281.txt"},"281\/23":{"dl_date":1700519135,"dl_url":"https:\/\/www.mynavyhr.navy.mil\/Portals\/55\/Messages\/NAVADMIN\/NAV2023\/NAV23281.txt"},"282\/22":{"dl_date":1671382442,"dl_url":"https:\/\/www.mynavyhr.navy.mil\/Portals\/55\/Messages\/NAVADMIN\/NAV2022\/NAV22282.txt"},"282\/23":{"dl_date":1700600191,"dl_url":"https:\/\/www.mynavyhr.navy.mil\/Portals\/55\/Messages\/NAVADMIN\/NAV2023\/NAV23282.txt"},"283\/22":{"dl_date":1671382442,"dl_url":"https:\/\/www.mynavyhr.navy.mil\/Portals\/55\/Messages\/NAVADMIN\/NAV2022\/NAV22283.txt"},"283\/23":{"dl_date":1700704750,"dl_url":"https:\/\/www.mynavyhr.navy.mil\/Portals\/55\/Messages\/NAVADMIN\/NAV2023\/NAV23283.txt"},"284\/22":{"dl_date":1671382442,"dl_url":"https:\/\/www.mynavyhr.navy.mil\/Portals\/55\/Messages\/NAVADMIN\/NAV2022\/NAV22284.txt"},"284\/23":{"dl_date":1700704750,"dl_url":"https:\/\/www.mynavyhr.navy.mil\/Portals\/55\/Messages\/NAVADMIN\/NAV2023\/NAV23284.txt"},"285\/22":{"dl_date":1671577595,"dl_url":"https:\/\/www.mynavyhr.navy.mil\/Portals\/55\/Messages\/NAVADMIN\/NAV2022\/NAV22285.txt"},"285\/23":{"dl_date":1701140807,"dl_url":"https:\/\/www.mynavyhr.navy.mil\/Portals\/55\/Messages\/NAVADMIN\/NAV2023\/NAV23285.txt"},"286\/22":{"dl_date":1671577594,"dl_url":"https:\/\/www.mynavyhr.navy.mil\/Portals\/55\/Messages\/NAVADMIN\/NAV2022\/NAV22286.txt"},"286\/23":{"dl_date":1701222710,"dl_url":"https:\/\/www.mynavyhr.navy.mil\/Portals\/55\/Messages\/NAVADMIN\/NAV2023\/NAV23286.txt"},"287\/22":{"dl_date":1671577594,"dl_url":"https:\/\/www.mynavyhr.navy.mil\/Portals\/55\/Messages\/NAVADMIN\/NAV2022\/NAV22287.txt"},"287\/23":{"dl_date":1701222710,"dl_url":"https:\/\/www.mynavyhr.navy.mil\/Portals\/55\/Messages\/NAVADMIN\/NAV2023\/NAV23287.txt"},"288\/22":{"dl_date":1671750374,"dl_url":"https:\/\/www.mynavyhr.navy.mil\/Portals\/55\/Messages\/NAVADMIN\/NAV2022\/NAV22288.txt"},"288\/23":{"dl_date":1701386452,"dl_url":"https:\/\/www.mynavyhr.navy.mil\/Portals\/55\/Messages\/NAVADMIN\/NAV2023\/NAV23288.txt"},"289\/22":{"dl_date":1671750374,"dl_url":"https:\/\/www.mynavyhr.navy.mil\/Portals\/55\/Messages\/NAVADMIN\/NAV2022\/NAV22289.txt"},"289\/23":{"dl_date":1701469278,"dl_url":"https:\/\/www.mynavyhr.navy.mil\/Portals\/55\/Messages\/NAVADMIN\/NAV2023\/NAV23289.txt"},"290\/22":{"dl_date":1671750374,"dl_url":"https:\/\/www.mynavyhr.navy.mil\/Portals\/55\/Messages\/NAVADMIN\/NAV2022\/NAV22290.txt"},"290\/23":{"dl_date":1701907685,"dl_url":"https:\/\/www.mynavyhr.navy.mil\/Portals\/55\/Messages\/NAVADMIN\/NAV2023\/NAV23290.txt"},"291\/22":{"dl_date":1671750374,"dl_url":"https:\/\/www.mynavyhr.navy.mil\/Portals\/55\/Messages\/NAVADMIN\/NAV2022\/NAV22291.txt"},"291\/23":{"dl_date":1702563516,"dl_url":"https:\/\/www.mynavyhr.navy.mil\/Portals\/55\/Messages\/NAVADMIN\/NAV2023\/NAV23291.txt"},"292\/22":{"dl_date":1672366415,"dl_url":"https:\/\/www.mynavyhr.navy.mil\/Portals\/55\/Messages\/NAVADMIN\/NAV2022\/NAV22292.txt"},"292\/23":{"dl_date":1702563516,"dl_url":"https:\/\/www.mynavyhr.navy.mil\/Portals\/55\/Messages\/NAVADMIN\/NAV2023\/NAV23292.txt"},"293\/23":{"dl_date":1702071298,"dl_url":"https:\/\/www.mynavyhr.navy.mil\/Portals\/55\/Messages\/NAVADMIN\/NAV2023\/NAV23293.txt"},"294\/23":{"dl_date":1702071298,"dl_url":"https:\/\/www.mynavyhr.navy.mil\/Portals\/55\/Messages\/NAVADMIN\/NAV2023\/NAV23294.txt"},"295\/23":{"dl_date":1703712463,"dl_url":"https:\/\/www.mynavyhr.navy.mil\/Portals\/55\/Messages\/NAVADMIN\/NAV2023\/NAV23295.txt"},"296\/23":{"dl_date":1702563516,"dl_url":"https:\/\/www.mynavyhr.navy.mil\/Portals\/55\/Messages\/NAVADMIN\/NAV2023\/NAV23296.txt"},"297\/23":{"dl_date":1702563516,"dl_url":"https:\/\/www.mynavyhr.navy.mil\/Portals\/55\/Messages\/NAVADMIN\/NAV2023\/NAV23297.txt"},"298\/23":{"dl_date":1702691401,"dl_url":"https:\/\/www.mynavyhr.navy.mil\/Portals\/55\/Messages\/NAVADMIN\/NAV2023\/NAV23298.txt"},"299\/23":{"dl_date":1703272325,"dl_url":"https:\/\/www.mynavyhr.navy.mil\/Portals\/55\/Messages\/NAVADMIN\/NAV2023\/NAV23299.txt"},"300\/23":{"dl_date":1703272325,"dl_url":"https:\/\/www.mynavyhr.navy.mil\/Portals\/55\/Messages\/NAVADMIN\/NAV2023\/NAV23300.txt"},"301\/23":{"dl_date":1703272325,"dl_url":"https:\/\/www.mynavyhr.navy.mil\/Portals\/55\/Messages\/NAVADMIN\/NAV2023\/NAV23301.txt"},"302\/23":{"dl_date":1703272325,"dl_url":"https:\/\/www.mynavyhr.navy.mil\/Portals\/55\/Messages\/NAVADMIN\/NAV2023\/NAV23302.txt"},"303\/23":{"dl_date":1703272325,"dl_url":"https:\/\/www.mynavyhr.navy.mil\/Portals\/55\/Messages\/NAVADMIN\/NAV2023\/NAV23303.txt"},"304\/23":{"dl_date":1703802776,"dl_url":"https:\/\/www.mynavyhr.navy.mil\/Portals\/55\/Messages\/NAVADMIN\/NAV2023\/NAV23304.txt"},"305\/23":{"dl_date":1703802776,"dl_url":"https:\/\/www.mynavyhr.navy.mil\/Portals\/55\/Messages\/NAVADMIN\/NAV2023\/NAV23305.txt"},"332\/10":{"dl_date":1735748920,"dl_url":"https:\/\/www.mynavyhr.navy.mil\/Portals\/55\/Messages\/NAVADMIN\/NAV2010\/NAV10332.txt"},"373\/11":{"dl_date":1735748920,"dl_url":"https:\/\/www.mynavyhr.navy.mil\/Portals\/55\/Messages\/NAVADMIN\/NAV2011\/NAV11373.txt"}}